Workbook
Name Slicer_Year: #N/A

Sheet DASHBOARD

Sheet Real Sector

Sheet Monetary

Sheet Inflation

Sheet Labour

Sheet External

Sheet Fiscal

Sheet Summary

Sheet Control
A3: Row Labels | B3: Sum of Real_GDP_Growth | C3: Sum of GDP_Per_Capita_Growth | D3: Sum of Male_Wage_Growth | E3: Sum of Female_Wage_Growth | F3: Sum of Exports | G3: Sum of Imports | H3: Sum of Agriculture | I3: Sum of Industry | J3: Sum of Services | K3: Sum of Consumption_Contribution | W3: Row Labels | X3: Sum of Real_GDP_Growth | Y3: Sum of GDP_Per_Capita_Growth
A4: 2005 | B4: 11.62 | C4: 12.08 | D4: 87.79 | E4: 82.97 | F4: 44.81 | G4: 104.52 | H4: 4.02 | I4: 21.03 | J4: 74.05 | K4: 65.3 | W4: 1999 | X4: 2.82 | Y4: 3.07
A5: 2006 | B5: 12.83 | C5: 13.09 | D5: 88.56 | E5: 83.74 | F5: 41.95 | G5: 105.7 | H5: 3.06 | I5: 20.09 | J5: 75.05 | K5: 67.2 | W5: 2000 | X5: 5.84 | Y5: 6.09
A6: 2007 | B6: 10.41 | C6: 11.03 | D6: 88.94 | E6: 84.17 | F6: 40.39 | G6: 100.88 | H6: 3.03 | I6: 20.06 | J6: 76.01 | K6: 66.3 | W6: 2001 | X6: 6.46 | Y6: 7.08
A7: 2008 | B7: -3.39 | C7: -2.04 | D7: 89.88 | E7: 84.36 | F7: 41.23 | G7: 95.77 | H7: 3.01 | I7: 20.08 | J7: 76.01 | K7: 64.1 | W7: 2002 | X7: 7.67 | Y7: 8.09
A8: 2009 | B8: -16.04 | C8: -14.06 | D8: 89.25 | E8: 83.54 | F8: 43.4 | G8: 88.83 | H8: 3.04 | I8: 20.02 | J8: 76.04 | K8: 61.3 | W8: 2003 | X8: 8.43 | Y8: 9.05
A9: 2010 | B9: -3.66 | C9: -1.06 | D9: 88.88 | E9: 83.57 | F9: 54.37 | G9: 110.86 | H9: 4.01 | I9: 22.06 | J9: 73.03 | K9: 61.6 | W9: 2004 | X9: 8.73 | Y9: 9.09
A10: 2011 | B10: 3.04 | C10: 4.09 | D10: 89.02 | E10: 83.66 | F10: 61.8 | G10: 129.73 | H10: 4.03 | I10: 24 | J10: 71.07 | K10: 61.4 | W10: 2005 | X10: 11.62 | Y10: 12.08
A11: 2012 | B11: 7.31 | C11: 8.06 | D11: 89.27 | E11: 83.62 | F11: 63.83 | G11: 133.21 | H11: 4.05 | I11: 24.03 | J11: 71.02 | K11: 62.4 | W11: 2006 | X11: 12.83 | Y11: 13.09
A12: 2013 | B12: 2.01 | C12: 3.02 | D12: 89.24 | E12: 83.52 | F12: 62.58 | G12: 129.68 | H12: 4.01 | I12: 23.08 | J12: 72.01 | K12: 62.1 | W12: 2007 | X12: 10.41 | Y12: 11.03
A13: 2014 | B13: 2.09 | C13: 3.01 | D13: 89.28 | E13: 83.41 | F13: 63.57 | G13: 130.04 | H13: 3.07 | I13: 23.04 | J13: 72.09 | K13: 61.3 | W13: 2008 | X13: -3.39 | Y13: -2.04
A14: Grand Total | B14: 26.22 | C14: 37.22 | D14: 890.11 | E14: 836.56 | F14: 517.93 | G14: 1129.22 | H14: 35.33 | I14: 217.49 | J14: 736.38 | K14: 633 | W14: 2009 | X14: -16.04 | Y14: -14.06
W15: 2010 | X15: -3.66 | Y15: -1.06
W16: 2011 | X16: 3.04 | Y16: 4.09
W17: 2012 | X17: 7.31 | Y17: 8.06
W18: 2013 | X18: 2.01 | Y18: 3.02
W19: 2014 | X19: 2.09 | Y19: 3.01
W20: 2015 | X20: 3.78 | Y20: 4.06
W21: 2016 | X21: 2.55 | Y21: 3.05
W22: 2017 | X22: 3.04 | Y22: 4.03
W23: 2018 | X23: 4.31 | Y23: 5.01
W24: 2019 | X24: 0.68 | Y24: 1.04
W25: 2020 | X25: -3.47 | Y25: -2.08
W26: 2021 | X26: 6.94 | Y26: 7.08
... W29: 2024 | X29: -0.44 | Y29: 0.04
W30: Grand Total | X30: 88.22 | Y30: 106.93
A36: Row Labels | B36: Sum of Male_Wage_Growth | C36: Sum of Female_Wage_Growth
A37: 1999 | B37: 83.11 | C37: 79.7
A38: 2000 | B38: 84.61 | C38: 81.48
A39: 2001 | B39: 84.25 | C39: 80.16
A40: 2002 | B40: 85.46 | C40: 80.83
A41: 2003 | B41: 85.6 | C41: 81.33
A42: 2004 | B42: 85.13 | C42: 82.02
A43: 2005 | B43: 87.79 | C43: 82.97
A44: 2006 | B44: 88.56 | C44: 83.74
A45: 2007 | B45: 88.94 | C45: 84.17
A46: 2008 | B46: 89.88 | C46: 84.36
A47: 2009 | B47: 89.25 | C47: 83.54
A48: 2010 | B48: 88.88 | C48: 83.57
... A62: 2024 | B62: 88.47 | C62: 84
A63: Grand Total | B63: 2290.25 | C63: 2162.36
A66: Row Labels | B66: Sum of Exports | C66: Sum of Imports
A67: 1999 | B67: 36.03 | C67: 82.15
A68: 2000 | B68: 37.72 | C68: 83.61
A69: 2001 | B69: 38.8 | C69: 88.18
A70: 2002 | B70: 37.76 | C70: 85.98
A71: 2003 | B71: 37.74 | C71: 88.58
A72: 2004 | B72: 40.63 | C72: 97.24
A73: 2005 | B73: 44.81 | C73: 104.52
A74: 2006 | B74: 41.95 | C74: 105.7
A75: 2007 | B75: 40.39 | C75: 100.88
A76: 2008 | B76: 41.23 | C76: 95.77
A77: 2009 | B77: 43.4 | C77: 88.83
A78: 2010 | B78: 54.37 | C78: 110.86
... A92: 2024 | B92: 64.62 | C92: 67.18
A93: Grand Total | B93: 1399.72 | C93: 2911.23

Sheet Processing
A1: Year | B1: X | C1: indent | D1: Real_GDP_Growth | E1: GDP_Per_Capita_Growth | F1: indent C | G1: Cursor I | H1: Cursor E | I1: Marker | J1: Lable | L1: Sum of Male_Wage_Growth | M1: Sum of Female_Wage_Growth | N1: Ratio | O1: Ratio Growth | Q1: X | R1: Y | T1: Sum of Exports | U1: Sum of Imports | V1: Ratio | W1: Ratio index | Y1: X | Z1: Y | AB1: Sum of Agriculture | AC1: Sum of Industry | AD1: Sum of Services | AG1: Sector | AH1: Value | AJ1: Year | AK1: Policy Interest Rate | AL1: Market Interest Rate | AN1: {=MacroData[Year]} -> 1999 | AO1: {=MacroData[Money_Supply]} -> 15 | AR1: Year | AS1: Headline Inflation | AT1: Core Inflation | AU1: Food Inflation | AV1: Non-Food Inflation | AW1: PPI | AY1: PPI | AZ1: =INDEX(MacroData[PPI], MATCH(Control!A4, MacroData[Year],0)) -> 8.5 | BB1: Year | BC1: Unemployment_Rate | BD1: Labour_Force_Part_Rate | BE1: Female_LFPR | BF1: Male_Wage_Growth | BG1: Female_Wage_Growth | BH1: Wage Gap | BJ1: Year | BK1: Exports | BL1: Imports | BM1: Exchange_Rate_Movement | BN1: FDI | BO1: Trade Balance | BS1: Year | BT1: Gov_Expenditure | BU1: Budget_Deficit | BV1: Public_Debt | BW1: Revenue_Taxation
A2: 1999 | B2: =RIGHT(A2, 2) -> 99 | C2: =$C$28 -> 0.5236 | D2: =GETPIVOTDATA(""&D$1,Control!$W$3,"Year",""&$A2) -> 2.82 | E2: =GETPIVOTDATA(""&E$1,Control!$W$3,"Year",""&$A2) -> 3.07 | F2: =C2 -> 0.5236 | G2: =IFERROR(GETPIVOTDATA(""&D$1,Control!$B$3,"Year",""&$A2),NA()) -> #N/A | H2: =IFERROR(GETPIVOTDATA(""&E$1,Control!$B$3,"Year",""&$A2),NA()) -> #N/A | I2: =C2+G2 -> #N/A | J2: =IF(G2>1,TEXT(ROUND(G2/1,0),"0"),G2) -> #N/A | L2: =GETPIVOTDATA(""&L$1,Control!$B$36,"Year",""&$A2) -> 83.11 | M2: =GETPIVOTDATA(""&M$1,Control!$B$36,"Year",""&$A2) -> 79.7 | N2: =L2/SUM(L2:M2) -> 0.51047233 | O2: =N28 -> 0.51550673 | P2: =1-O2 -> 0.48449327 | Q2: 0 | R2: 1 | T2: =GETPIVOTDATA(""&T$1,Control!$B$66,"Year",""&$A2) -> 36.03 | U2: =GETPIVOTDATA(""&U$1,Control!$C$66,"Year",""&$A2) -> 82.15 | V2: =T2/SUM(T2:U2) -> 0.30487392 | W2: =V28 -> 0.31444009 | X2: =1-W2 -> 0.68555991 | Y2: 0 | Z2: 1 | AB2: {=MacroData[Agriculture]} -> 4.5 | AC2: {=MacroData[Industry]} -> 23.08 | AD2: {=MacroData[Services]} -> 71.07 | AG2: Agriculture | AH2: =INDEX(MacroData[Agriculture],MATCH(Control!A4, MacroData[Year],0)) -> 4.02 | AJ2: =MacroData[[#This Row],[Year]] -> 1999 | AK2: =MacroData[[#This Row],[Policy_Interest_Rate]] -> 14.2 | AL2: =MacroData[[#This Row],[Market_Interest_Rate]] -> 14.2 | AN2: 2000 | AO2: 28 | AR2: =MacroData[[#This Row],[Year]] -> 1999 | AS2: =MacroData[[#This Row],[Headline_Inflation]] -> 2.36 | AT2: =MacroData[[#This Row],[Core_Inflation]] -> 2.9 | AU2: =MacroData[[#This Row],[Food_Inflation]] -> -2 | AV2: =MacroData[[#This Row],[Non_Food_Inflation]] -> 4.1 | AW2: =MacroData[[#This Row],[PPI]] -> -2 | AY2: Headline | AZ2: =INDEX(MacroData[Headline_Inflation], MATCH(Control!A4, MacroData[Year],0)) -> 6.75 | BB2: =MacroData[[#This Row],[Year]] -> 1999 | BC2: =MacroData[[#This Row],[Unemployment_Rate]] -> 13.79 | BD2: =MacroData[[#This Row],[Labour_Force_Part_Rate]] -> 42.32 | BE2: =MacroData[[#This Row],[Female_LFPR]] -> 47.59 | BF2: =INDEX(MacroData[Male_Wage_Growth], MATCH(Control!A4, MacroData[Year],0)) -> 87.79 | BG2: =INDEX(MacroData[Female_Wage_Growth], MATCH(Control!A4, MacroData[Year],0)) -> 82.97 | BH2: =INDEX(MacroData[Male_Wage_Growth], MATCH(Control!A4, MacroData[Year],0)) - INDEX(MacroData[Female_Wage_Growth], MATCH(Control!A4, MacroData[Year],0)) -> 4.82 | BJ2: =MacroData[[#This Row],[Year]] -> 1999 | BK2: =MacroData[[#This Row],[Exports]] -> 36.03 | BL2: =MacroData[[#This Row],[Imports]] -> 82.15 | BM2: =MacroData[[#This Row],[Exchange_Rate_Movement]] -> 0.58 | BN2: =MacroData[[#This Row],[FDI]] -> 4.75 | BO2: =Table5[[#This Row],[Exports]] - Table5[[#This Row],[Imports]] -> -46.12 | BQ2: =INDEX(MacroData[FDI], MATCH(Control!A4, MacroData[Year],0)) -> 4.97 | BS2: =MacroData[[#This Row],[Year]] -> 1999 | BT2: =MacroData[[#This Row],[Gov_Expenditure]] -> 40.4 | BU2: =MacroData[[#This Row],[Budget_Deficit]] -> -3.5 | BV2: =MacroData[[#This Row],[Public_Debt]] -> 14.8 | BW2: =MacroData[[#This Row],[Revenue_Taxation]] -> 21
A3: 2000 | B3: =RIGHT(A3, 2) -> 00 | C3: =$C$28 -> 0.5236 | D3: =GETPIVOTDATA(""&D$1,Control!$W$3,"Year",""&$A3) -> 5.84 | E3: =GETPIVOTDATA(""&E$1,Control!$W$3,"Year",""&$A3) -> 6.09 | F3: =C3 -> 0.5236 | G3: =IFERROR(GETPIVOTDATA(""&D$1,Control!$B$3,"Year",""&$A3),NA()) -> #N/A | H3: =IFERROR(GETPIVOTDATA(""&E$1,Control!$B$3,"Year",""&$A3),NA()) -> #N/A | I3: =C3+G3 -> #N/A | J3: =IF(G3>1,TEXT(ROUND(G3/1,0),"0"),G3) -> #N/A | L3: =GETPIVOTDATA(""&L$1,Control!$B$36,"Year",""&$A3) -> 84.61 | M3: =GETPIVOTDATA(""&M$1,Control!$B$36,"Year",""&$A3) -> 81.48 | N3: =L3/SUM(L3:M3) -> 0.5094226 | Q3: =SIN(O2*2*PI()) -> -0.097277559 | R3: =COS(O2*2*PI()) -> -0.99525729 | T3: =GETPIVOTDATA(""&T$1,Control!$B$66,"Year",""&$A3) -> 37.72 | U3: =GETPIVOTDATA(""&U$1,Control!$C$66,"Year",""&$A3) -> 83.61 | V3: =T3/SUM(T3:U3) -> 0.31088766 | Y3: =SIN(W2*2*PI()) -> 0.91914611 | Z3: =COS(W2*2*PI()) -> -0.39391678 | AB3: 4.09 | AC3: 23.05 | AD3: 71.06 | AG3: Industry | AH3: =INDEX(MacroData[Industry], MATCH(Control!A4, MacroData[Year],0)) -> 21.03 | AJ3: =MacroData[[#This Row],[Year]] -> 2000 | AK3: =MacroData[[#This Row],[Policy_Interest_Rate]] -> 12.5 | AL3: =MacroData[[#This Row],[Market_Interest_Rate]] -> 12.5 | AN3: 2001 | AO3: 21 | AR3: =MacroData[[#This Row],[Year]] -> 2000 | AS3: =MacroData[[#This Row],[Headline_Inflation]] -> 2.65 | AT3: =MacroData[[#This Row],[Core_Inflation]] -> 2.4 | AU3: =MacroData[[#This Row],[Food_Inflation]] -> -0.1 | AV3: =MacroData[[#This Row],[Non_Food_Inflation]] -> 3.1 | AW3: =MacroData[[#This Row],[PPI]] -> 0.6 | AY3: Core | AZ3: =INDEX(MacroData[Core_Inflation], MATCH(Control!A4, MacroData[Year],0)) -> 5.1 | BB3: =MacroData[[#This Row],[Year]] -> 2000 | BC3: =MacroData[[#This Row],[Unemployment_Rate]] -> 14.21 | BD3: =MacroData[[#This Row],[Labour_Force_Part_Rate]] -> 38.44 | BE3: =MacroData[[#This Row],[Female_LFPR]] -> 48.04 | BF3: =INDEX(MacroData[Male_Wage_Growth], MATCH(Control!A5, MacroData[Year],0)) -> 88.56 | BG3: =INDEX(MacroData[Female_Wage_Growth], MATCH(Control!A5, MacroData[Year],0)) -> 83.74 | BH3: =INDEX(MacroData[Male_Wage_Growth], MATCH(Control!A5, MacroData[Year],0)) - INDEX(MacroData[Female_Wage_Growth], MATCH(Control!A5, MacroData[Year],0)) -> 4.82 | BJ3: =MacroData[[#This Row],[Year]] -> 2000 | BK3: =MacroData[[#This Row],[Exports]] -> 37.72 | BL3: =MacroData[[#This Row],[Imports]] -> 83.61 | BM3: =MacroData[[#This Row],[Exchange_Rate_Movement]] -> 0.61 | BN3: =MacroData[[#This Row],[FDI]] -> 4.18 | BO3: =Table5[[#This Row],[Exports]] - Table5[[#This Row],[Imports]] -> -45.89 | BS3: =MacroData[[#This Row],[Year]] -> 2000 | BT3: =MacroData[[#This Row],[Gov_Expenditure]] -> 37 | BU3: =MacroData[[#This Row],[Budget_Deficit]] -> -2.6 | BV3: =MacroData[[#This Row],[Public_Debt]] -> 15.1 | BW3: =MacroData[[#This Row],[Revenue_Taxation]] -> 23
A4: 2001 | B4: =RIGHT(A4, 2) -> 01 | C4: =$C$28 -> 0.5236 | D4: =GETPIVOTDATA(""&D$1,Control!$W$3,"Year",""&$A4) -> 6.46 | E4: =GETPIVOTDATA(""&E$1,Control!$W$3,"Year",""&$A4) -> 7.08 | F4: =C4 -> 0.5236 | G4: =IFERROR(GETPIVOTDATA(""&D$1,Control!$B$3,"Year",""&$A4),NA()) -> #N/A | H4: =IFERROR(GETPIVOTDATA(""&E$1,Control!$B$3,"Year",""&$A4),NA()) -> #N/A | I4: =C4+G4 -> #N/A | J4: =IF(G4>1,TEXT(ROUND(G4/1,0),"0"),G4) -> #N/A | L4: =GETPIVOTDATA(""&L$1,Control!$B$36,"Year",""&$A4) -> 84.25 | M4: =GETPIVOTDATA(""&M$1,Control!$B$36,"Year",""&$A4) -> 80.16 | N4: =L4/SUM(L4:M4) -> 0.51243842 | T4: =GETPIVOTDATA(""&T$1,Control!$B$66,"Year",""&$A4) -> 38.8 | U4: =GETPIVOTDATA(""&U$1,Control!$C$66,"Year",""&$A4) -> 88.18 | V4: =T4/SUM(T4:U4) -> 0.30555993 | AB4: 4.07 | AC4: 23.01 | AD4: 72.02 | AG4: Services | AH4: =INDEX(MacroData[Services], MATCH(Control!A4, MacroData[Year],0)) -> 74.05 | AJ4: =MacroData[[#This Row],[Year]] -> 2001 | AK4: =MacroData[[#This Row],[Policy_Interest_Rate]] -> 11.1 | AL4: =MacroData[[#This Row],[Market_Interest_Rate]] -> 11.1 | AN4: 2002 | AO4: 21 | AR4: =MacroData[[#This Row],[Year]] -> 2001 | AS4: =MacroData[[#This Row],[Headline_Inflation]] -> 2.49 | AT4: =MacroData[[#This Row],[Core_Inflation]] -> 2.2 | AU4: =MacroData[[#This Row],[Food_Inflation]] -> 3.8 | AV4: =MacroData[[#This Row],[Non_Food_Inflation]] -> 2 | AW4: =MacroData[[#This Row],[PPI]] -> 0.2 | AY4: Food | AZ4: =INDEX(MacroData[Food_Inflation], MATCH(Control!A4, MacroData[Year],0)) -> 8.8 | BB4: =MacroData[[#This Row],[Year]] -> 2001 | BC4: =MacroData[[#This Row],[Unemployment_Rate]] -> 13.82 | BD4: =MacroData[[#This Row],[Labour_Force_Part_Rate]] -> 37.4 | BE4: =MacroData[[#This Row],[Female_LFPR]] -> 48.77 | BF4: =INDEX(MacroData[Male_Wage_Growth], MATCH(Control!A6, MacroData[Year],0)) -> 88.94 | BG4: =INDEX(MacroData[Female_Wage_Growth], MATCH(Control!A6, MacroData[Year],0)) -> 84.17 | BH4: =INDEX(MacroData[Male_Wage_Growth], MATCH(Control!A6, MacroData[Year],0)) - INDEX(MacroData[Female_Wage_Growth], MATCH(Control!A6, MacroData[Year],0)) -> 4.77 | BJ4: =MacroData[[#This Row],[Year]] -> 2001 | BK4: =MacroData[[#This Row],[Exports]] -> 38.8 | BL4: =MacroData[[#This Row],[Imports]] -> 88.18 | BM4: =MacroData[[#This Row],[Exchange_Rate_Movement]] -> 0.62 | BN4: =MacroData[[#This Row],[FDI]] -> 2.12 | BO4: =Table5[[#This Row],[Exports]] - Table5[[#This Row],[Imports]] -> -49.38 | BS4: =MacroData[[#This Row],[Year]] -> 2001 | BT4: =MacroData[[#This Row],[Gov_Expenditure]] -> 35 | BU4: =MacroData[[#This Row],[Budget_Deficit]] -> -2 | BV4: =MacroData[[#This Row],[Public_Debt]] -> 17.8 | BW4: =MacroData[[#This Row],[Revenue_Taxation]] -> 25 | BY4: =INDEX(MacroData[Public_Debt], MATCH(Control!A4, MacroData[Year],0)) -> 12.5
A5: 2002 | B5: =RIGHT(A5, 2) -> 02 | C5: =$C$28 -> 0.5236 | D5: =GETPIVOTDATA(""&D$1,Control!$W$3,"Year",""&$A5) -> 7.67 | E5: =GETPIVOTDATA(""&E$1,Control!$W$3,"Year",""&$A5) -> 8.09 | F5: =C5 -> 0.5236 | G5: =IFERROR(GETPIVOTDATA(""&D$1,Control!$B$3,"Year",""&$A5),NA()) -> #N/A | H5: =IFERROR(GETPIVOTDATA(""&E$1,Control!$B$3,"Year",""&$A5),NA()) -> #N/A | I5: =C5+G5 -> #N/A | J5: =IF(G5>1,TEXT(ROUND(G5/1,0),"0"),G5) -> #N/A | L5: =GETPIVOTDATA(""&L$1,Control!$B$36,"Year",""&$A5) -> 85.46 | M5: =GETPIVOTDATA(""&M$1,Control!$B$36,"Year",""&$A5) -> 80.83 | N5: =L5/SUM(L5:M5) -> 0.51392146 | T5: =GETPIVOTDATA(""&T$1,Control!$B$66,"Year",""&$A5) -> 37.76 | U5: =GETPIVOTDATA(""&U$1,Control!$C$66,"Year",""&$A5) -> 85.98 | V5: =T5/SUM(T5:U5) -> 0.30515597 | AB5: 4.07 | AC5: 22.08 | AD5: 72.05 | AH5: =SUM(AH2:AH4) -> 99.1 | AJ5: =MacroData[[#This Row],[Year]] -> 2002 | AK5: =MacroData[[#This Row],[Policy_Interest_Rate]] -> 8.8 | AL5: =MacroData[[#This Row],[Market_Interest_Rate]] -> 8.8 | AN5: 2003 | AO5: 19 | AR5: =MacroData[[#This Row],[Year]] -> 2002 | AS5: =MacroData[[#This Row],[Headline_Inflation]] -> 1.94 | AT5: =MacroData[[#This Row],[Core_Inflation]] -> 2 | AU5: =MacroData[[#This Row],[Food_Inflation]] -> 1.5 | AV5: =MacroData[[#This Row],[Non_Food_Inflation]] -> 1.8 | AW5: =MacroData[[#This Row],[PPI]] -> 1 | AY5: Non-Food | AZ5: =INDEX(MacroData[Non_Food_Inflation], MATCH(Control!A4, MacroData[Year],0)) -> 5.9 | BB5: =MacroData[[#This Row],[Year]] -> 2002 | BC5: =MacroData[[#This Row],[Unemployment_Rate]] -> 13.83 | BD5: =MacroData[[#This Row],[Labour_Force_Part_Rate]] -> 37.85 | BE5: =MacroData[[#This Row],[Female_LFPR]] -> 48.74 | BF5: =INDEX(MacroData[Male_Wage_Growth], MATCH(Control!A7, MacroData[Year],0)) -> 89.88 | BG5: =INDEX(MacroData[Female_Wage_Growth], MATCH(Control!A7, MacroData[Year],0)) -> 84.36 | BH5: =INDEX(MacroData[Male_Wage_Growth], MATCH(Control!A7, MacroData[Year],0)) - INDEX(MacroData[Female_Wage_Growth], MATCH(Control!A7, MacroData[Year],0)) -> 5.52 | BJ5: =MacroData[[#This Row],[Year]] -> 2002 | BK5: =MacroData[[#This Row],[Exports]] -> 37.76 | BL5: =MacroData[[#This Row],[Imports]] -> 85.98 | BM5: =MacroData[[#This Row],[Exchange_Rate_Movement]] -> 0.61 | BN5: =MacroData[[#This Row],[FDI]] -> 1.73 | BO5: =Table5[[#This Row],[Exports]] - Table5[[#This Row],[Imports]] -> -48.22 | BS5: =MacroData[[#This Row],[Year]] -> 2002 | BT5: =MacroData[[#This Row],[Gov_Expenditure]] -> 35.4 | BU5: =MacroData[[#This Row],[Budget_Deficit]] -> -2.6 | BV5: =MacroData[[#This Row],[Public_Debt]] -> 15.4 | BW5: =MacroData[[#This Row],[Revenue_Taxation]] -> 24
A6: 2003 | B6: =RIGHT(A6, 2) -> 03 | C6: =$C$28 -> 0.5236 | D6: =GETPIVOTDATA(""&D$1,Control!$W$3,"Year",""&$A6) -> 8.43 | E6: =GETPIVOTDATA(""&E$1,Control!$W$3,"Year",""&$A6) -> 9.05 | F6: =C6 -> 0.5236 | G6: =IFERROR(GETPIVOTDATA(""&D$1,Control!$B$3,"Year",""&$A6),NA()) -> #N/A | H6: =IFERROR(GETPIVOTDATA(""&E$1,Control!$B$3,"Year",""&$A6),NA()) -> #N/A | I6: =C6+G6 -> #N/A | J6: =IF(G6>1,TEXT(ROUND(G6/1,0),"0"),G6) -> #N/A | L6: =GETPIVOTDATA(""&L$1,Control!$B$36,"Year",""&$A6) -> 85.6 | M6: =GETPIVOTDATA(""&M$1,Control!$B$36,"Year",""&$A6) -> 81.33 | N6: =L6/SUM(L6:M6) -> 0.51278979 | T6: =GETPIVOTDATA(""&T$1,Control!$B$66,"Year",""&$A6) -> 37.74 | U6: =GETPIVOTDATA(""&U$1,Control!$C$66,"Year",""&$A6) -> 88.58 | V6: =T6/SUM(T6:U6) -> 0.29876504 | AB6: 4.03 | AC6: 22.01 | AD6: 73.06 | AG6: Indicator | AH6: Value | AJ6: =MacroData[[#This Row],[Year]] -> 2003 | AK6: =MacroData[[#This Row],[Policy_Interest_Rate]] -> 7.4 | AL6: =MacroData[[#This Row],[Market_Interest_Rate]] -> 7.4 | AN6: 2004 | AO6: 27 | AR6: =MacroData[[#This Row],[Year]] -> 2003 | AS6: =MacroData[[#This Row],[Headline_Inflation]] -> 2.94 | AT6: =MacroData[[#This Row],[Core_Inflation]] -> 2.1 | AU6: =MacroData[[#This Row],[Food_Inflation]] -> 2.4 | AV6: =MacroData[[#This Row],[Non_Food_Inflation]] -> 3 | AW6: =MacroData[[#This Row],[PPI]] -> 3.2 | BB6: =MacroData[[#This Row],[Year]] -> 2003 | BC6: =MacroData[[#This Row],[Unemployment_Rate]] -> 12.06 | BD6: =MacroData[[#This Row],[Labour_Force_Part_Rate]] -> 38.87 | BE6: =MacroData[[#This Row],[Female_LFPR]] -> 48.94 | BF6: =INDEX(MacroData[Male_Wage_Growth], MATCH(Control!A8, MacroData[Year],0)) -> 89.25 | BG6: =INDEX(MacroData[Female_Wage_Growth], MATCH(Control!A8, MacroData[Year],0)) -> 83.54 | BH6: =INDEX(MacroData[Male_Wage_Growth], MATCH(Control!A8, MacroData[Year],0)) - INDEX(MacroData[Female_Wage_Growth], MATCH(Control!A8, MacroData[Year],0)) -> 5.71 | BJ6: =MacroData[[#This Row],[Year]] -> 2003 | BK6: =MacroData[[#This Row],[Exports]] -> 37.74 | BL6: =MacroData[[#This Row],[Imports]] -> 88.58 | BM6: =MacroData[[#This Row],[Exchange_Rate_Movement]] -> 0.57 | BN6: =MacroData[[#This Row],[FDI]] -> 2.82 | BO6: =Table5[[#This Row],[Exports]] - Table5[[#This Row],[Imports]] -> -50.84 | BS6: =MacroData[[#This Row],[Year]] -> 2003 | BT6: =MacroData[[#This Row],[Gov_Expenditure]] -> 34.4 | BU6: =MacroData[[#This Row],[Budget_Deficit]] -> -1.7 | BV6: =MacroData[[#This Row],[Public_Debt]] -> 15.4 | BW6: =MacroData[[#This Row],[Revenue_Taxation]] -> 23 | BY6: =INDEX(MacroData[Revenue_Taxation], MATCH(Control!A4, MacroData[Year],0)) -> 24
A7: 2004 | B7: =RIGHT(A7, 2) -> 04 | C7: =$C$28 -> 0.5236 | D7: =GETPIVOTDATA(""&D$1,Control!$W$3,"Year",""&$A7) -> 8.73 | E7: =GETPIVOTDATA(""&E$1,Control!$W$3,"Year",""&$A7) -> 9.09 | F7: =C7 -> 0.5236 | G7: =IFERROR(GETPIVOTDATA(""&D$1,Control!$B$3,"Year",""&$A7),NA()) -> #N/A | H7: =IFERROR(GETPIVOTDATA(""&E$1,Control!$B$3,"Year",""&$A7),NA()) -> #N/A | I7: =C7+G7 -> #N/A | J7: =IF(G7>1,TEXT(ROUND(G7/1,0),"0"),G7) -> #N/A | L7: =GETPIVOTDATA(""&L$1,Control!$B$36,"Year",""&$A7) -> 85.13 | M7: =GETPIVOTDATA(""&M$1,Control!$B$36,"Year",""&$A7) -> 82.02 | N7: =L7/SUM(L7:M7) -> 0.50930302 | T7: =GETPIVOTDATA(""&T$1,Control!$B$66,"Year",""&$A7) -> 40.63 | U7: =GETPIVOTDATA(""&U$1,Control!$C$66,"Year",""&$A7) -> 97.24 | V7: =T7/SUM(T7:U7) -> 0.2946979 | AB7: 4.05 | AC7: 21.05 | AD7: 74 | AG7: Consumption Contribution | AH7: =INDEX(MacroData[Consumption_Contribution],MATCH(Control!A4, MacroData[Year],0)) -> 65.3 | AJ7: =MacroData[[#This Row],[Year]] -> 2004 | AK7: =MacroData[[#This Row],[Policy_Interest_Rate]] -> 6.9 | AL7: =MacroData[[#This Row],[Market_Interest_Rate]] -> 6.9 | AN7: 2005 | AO7: 38 | AR7: =MacroData[[#This Row],[Year]] -> 2004 | AS7: =MacroData[[#This Row],[Headline_Inflation]] -> 6.19 | AT7: =MacroData[[#This Row],[Core_Inflation]] -> 4.4 | AU7: =MacroData[[#This Row],[Food_Inflation]] -> 9 | AV7: =MacroData[[#This Row],[Non_Food_Inflation]] -> 4.9 | AW7: =MacroData[[#This Row],[PPI]] -> 6.5 | BB7: =MacroData[[#This Row],[Year]] -> 2004 | BC7: =MacroData[[#This Row],[Unemployment_Rate]] -> 11.71 | BD7: =MacroData[[#This Row],[Labour_Force_Part_Rate]] -> 36.97 | BE7: =MacroData[[#This Row],[Female_LFPR]] -> 48.54 | BF7: =INDEX(MacroData[Male_Wage_Growth], MATCH(Control!A9, MacroData[Year],0)) -> 88.88 | BG7: =INDEX(MacroData[Female_Wage_Growth], MATCH(Control!A9, MacroData[Year],0)) -> 83.57 | BH7: =INDEX(MacroData[Male_Wage_Growth], MATCH(Control!A9, MacroData[Year],0)) - INDEX(MacroData[Female_Wage_Growth], MATCH(Control!A9, MacroData[Year],0)) -> 5.31 | BJ7: =MacroData[[#This Row],[Year]] -> 2004 | BK7: =MacroData[[#This Row],[Exports]] -> 40.63 | BL7: =MacroData[[#This Row],[Imports]] -> 97.24 | BM7: =MacroData[[#This Row],[Exchange_Rate_Movement]] -> 0.54 | BN7: =MacroData[[#This Row],[FDI]] -> 4.28 | BO7: =Table5[[#This Row],[Exports]] - Table5[[#This Row],[Imports]] -> -56.61 | BS7: =MacroData[[#This Row],[Year]] -> 2004 | BT7: =MacroData[[#This Row],[Gov_Expenditure]] -> 34.8 | BU7: =MacroData[[#This Row],[Budget_Deficit]] -> -1 | BV7: =MacroData[[#This Row],[Public_Debt]] -> 15.3 | BW7: =MacroData[[#This Row],[Revenue_Taxation]] -> 23
A8: 2005 | B8: =RIGHT(A8, 2) -> 05 | C8: =$C$28 -> 0.5236 | D8: =GETPIVOTDATA(""&D$1,Control!$W$3,"Year",""&$A8) -> 11.62 | E8: =GETPIVOTDATA(""&E$1,Control!$W$3,"Year",""&$A8) -> 12.08 | F8: =C8 -> 0.5236 | G8: =IFERROR(GETPIVOTDATA(""&D$1,Control!$B$3,"Year",""&$A8),NA()) -> 11.62 | H8: =IFERROR(GETPIVOTDATA(""&E$1,Control!$B$3,"Year",""&$A8),NA()) -> 12.08 | I8: =C8+G8 -> 12.1436 | J8: =IF(G8>1,TEXT(ROUND(G8/1,0),"0"),G8) -> 12 | L8: =GETPIVOTDATA(""&L$1,Control!$B$36,"Year",""&$A8) -> 87.79 | M8: =GETPIVOTDATA(""&M$1,Control!$B$36,"Year",""&$A8) -> 82.97 | N8: =L8/SUM(L8:M8) -> 0.51411338 | T8: =GETPIVOTDATA(""&T$1,Control!$B$66,"Year",""&$A8) -> 44.81 | U8: =GETPIVOTDATA(""&U$1,Control!$C$66,"Year",""&$A8) -> 104.52 | V8: =T8/SUM(T8:U8) -> 0.30007366 | AB8: 4.02 | AC8: 21.03 | AD8: 74.05 | AG8: Sector Total | AH8: =AH5 -> 99.1 | AJ8: =MacroData[[#This Row],[Year]] -> 2005 | AK8: =MacroData[[#This Row],[Policy_Interest_Rate]] -> 5.5 | AL8: =MacroData[[#This Row],[Market_Interest_Rate]] -> 5.5 | AN8: 2006 | AO8: 41 | AR8: =MacroData[[#This Row],[Year]] -> 2005 | AS8: =MacroData[[#This Row],[Headline_Inflation]] -> 6.75 | AT8: =MacroData[[#This Row],[Core_Inflation]] -> 5.1 | AU8: =MacroData[[#This Row],[Food_Inflation]] -> 8.8 | AV8: =MacroData[[#This Row],[Non_Food_Inflation]] -> 5.9 | AW8: =MacroData[[#This Row],[PPI]] -> 8.5 | BB8: =MacroData[[#This Row],[Year]] -> 2005 | BC8: =MacroData[[#This Row],[Unemployment_Rate]] -> 10.03 | BD8: =MacroData[[#This Row],[Labour_Force_Part_Rate]] -> 38.05 | BE8: =MacroData[[#This Row],[Female_LFPR]] -> 48.49 | BF8: =INDEX(MacroData[Male_Wage_Growth], MATCH(Control!A10, MacroData[Year],0)) -> 89.02 | BG8: =INDEX(MacroData[Female_Wage_Growth], MATCH(Control!A10, MacroData[Year],0)) -> 83.66 | BH8: =INDEX(MacroData[Male_Wage_Growth], MATCH(Control!A10, MacroData[Year],0)) - INDEX(MacroData[Female_Wage_Growth], MATCH(Control!A10, MacroData[Year],0)) -> 5.36 | BJ8: =MacroData[[#This Row],[Year]] -> 2005 | BK8: =MacroData[[#This Row],[Exports]] -> 44.81 | BL8: =MacroData[[#This Row],[Imports]] -> 104.52 | BM8: =MacroData[[#This Row],[Exchange_Rate_Movement]] -> 0.56 | BN8: =MacroData[[#This Row],[FDI]] -> 4.97 | BO8: =Table5[[#This Row],[Exports]] - Table5[[#This Row],[Imports]] -> -59.71 | BS8: =MacroData[[#This Row],[Year]] -> 2005 | BT8: =MacroData[[#This Row],[Gov_Expenditure]] -> 35.8 | BU8: =MacroData[[#This Row],[Budget_Deficit]] -> -1.1 | BV8: =MacroData[[#This Row],[Public_Debt]] -> 12.5 | BW8: =MacroData[[#This Row],[Revenue_Taxation]] -> 24
A9: 2006 | B9: =RIGHT(A9, 2) -> 06 | C9: =$C$28 -> 0.5236 | D9: =GETPIVOTDATA(""&D$1,Control!$W$3,"Year",""&$A9) -> 12.83 | E9: =GETPIVOTDATA(""&E$1,Control!$W$3,"Year",""&$A9) -> 13.09 | F9: =C9 -> 0.5236 | G9: =IFERROR(GETPIVOTDATA(""&D$1,Control!$B$3,"Year",""&$A9),NA()) -> 12.83 | H9: =IFERROR(GETPIVOTDATA(""&E$1,Control!$B$3,"Year",""&$A9),NA()) -> 13.09 | I9: =C9+G9 -> 13.3536 | J9: =IF(G9>1,TEXT(ROUND(G9/1,0),"0"),G9) -> 13 | L9: =GETPIVOTDATA(""&L$1,Control!$B$36,"Year",""&$A9) -> 88.56 | M9: =GETPIVOTDATA(""&M$1,Control!$B$36,"Year",""&$A9) -> 83.74 | N9: =L9/SUM(L9:M9) -> 0.51398723 | T9: =GETPIVOTDATA(""&T$1,Control!$B$66,"Year",""&$A9) -> 41.95 | U9: =GETPIVOTDATA(""&U$1,Control!$C$66,"Year",""&$A9) -> 105.7 | V9: =T9/SUM(T9:U9) -> 0.28411785 | AB9: 3.06 | AC9: 20.09 | AD9: 75.05 | AJ9: =MacroData[[#This Row],[Year]] -> 2006 | AK9: =MacroData[[#This Row],[Policy_Interest_Rate]] -> 6.2 | AL9: =MacroData[[#This Row],[Market_Interest_Rate]] -> 6.2 | AN9: 2007 | AO9: 13 | AR9: =MacroData[[#This Row],[Year]] -> 2006 | AS9: =MacroData[[#This Row],[Headline_Inflation]] -> 6.54 | AT9: =MacroData[[#This Row],[Core_Inflation]] -> 5.8 | AU9: =MacroData[[#This Row],[Food_Inflation]] -> 9.5 | AV9: =MacroData[[#This Row],[Non_Food_Inflation]] -> 5.4 | AW9: =MacroData[[#This Row],[PPI]] -> 10 | BB9: =MacroData[[#This Row],[Year]] -> 2006 | BC9: =MacroData[[#This Row],[Unemployment_Rate]] -> 7.03 | BD9: =MacroData[[#This Row],[Labour_Force_Part_Rate]] -> 40.9 | BE9: =MacroData[[#This Row],[Female_LFPR]] -> 48.47 | BF9: =INDEX(MacroData[Male_Wage_Growth], MATCH(Control!A11, MacroData[Year],0)) -> 89.27 | BG9: =INDEX(MacroData[Female_Wage_Growth], MATCH(Control!A11, MacroData[Year],0)) -> 83.62 | BH9: =INDEX(MacroData[Male_Wage_Growth], MATCH(Control!A11, MacroData[Year],0)) - INDEX(MacroData[Female_Wage_Growth], MATCH(Control!A11, MacroData[Year],0)) -> 5.65 | BJ9: =MacroData[[#This Row],[Year]] -> 2006 | BK9: =MacroData[[#This Row],[Exports]] -> 41.95 | BL9: =MacroData[[#This Row],[Imports]] -> 105.7 | BM9: =MacroData[[#This Row],[Exchange_Rate_Movement]] -> 0.56 | BN9: =MacroData[[#This Row],[FDI]] -> 8.35 | BO9: =Table5[[#This Row],[Exports]] - Table5[[#This Row],[Imports]] -> -63.75 | BS9: =MacroData[[#This Row],[Year]] -> 2006 | BT9: =MacroData[[#This Row],[Gov_Expenditure]] -> 35.5 | BU9: =MacroData[[#This Row],[Budget_Deficit]] -> -0.5 | BV9: =MacroData[[#This Row],[Public_Debt]] -> 10.7 | BW9: =MacroData[[#This Row],[Revenue_Taxation]] -> 25
A10: 2007 | B10: =RIGHT(A10, 2) -> 07 | C10: =$C$28 -> 0.5236 | D10: =GETPIVOTDATA(""&D$1,Control!$W$3,"Year",""&$A10) -> 10.41 | E10: =GETPIVOTDATA(""&E$1,Control!$W$3,"Year",""&$A10) -> 11.03 | F10: =C10 -> 0.5236 | G10: =IFERROR(GETPIVOTDATA(""&D$1,Control!$B$3,"Year",""&$A10),NA()) -> 10.41 | H10: =IFERROR(GETPIVOTDATA(""&E$1,Control!$B$3,"Year",""&$A10),NA()) -> 11.03 | I10: =C10+G10 -> 10.9336 | J10: =IF(G10>1,TEXT(ROUND(G10/1,0),"0"),G10) -> 10 | L10: =GETPIVOTDATA(""&L$1,Control!$B$36,"Year",""&$A10) -> 88.94 | M10: =GETPIVOTDATA(""&M$1,Control!$B$36,"Year",""&$A10) -> 84.17 | N10: =L10/SUM(L10:M10) -> 0.51377737 | T10: =GETPIVOTDATA(""&T$1,Control!$B$66,"Year",""&$A10) -> 40.39 | U10: =GETPIVOTDATA(""&U$1,Control!$C$66,"Year",""&$A10) -> 100.88 | V10: =T10/SUM(T10:U10) -> 0.28590642 | AB10: 3.03 | AC10: 20.06 | AD10: 76.01 | AJ10: =MacroData[[#This Row],[Year]] -> 2007 | AK10: =MacroData[[#This Row],[Policy_Interest_Rate]] -> 8.5 | AL10: =MacroData[[#This Row],[Market_Interest_Rate]] -> 8.5 | AN10: 2008 | AO10: -2 | AR10: =MacroData[[#This Row],[Year]] -> 2007 | AS10: =MacroData[[#This Row],[Headline_Inflation]] -> 10.09 | AT10: =MacroData[[#This Row],[Core_Inflation]] -> 9 | AU10: =MacroData[[#This Row],[Food_Inflation]] -> 12.3 | AV10: =MacroData[[#This Row],[Non_Food_Inflation]] -> 9.1 | AW10: =MacroData[[#This Row],[PPI]] -> 15 | BB10: =MacroData[[#This Row],[Year]] -> 2007 | BC10: =MacroData[[#This Row],[Unemployment_Rate]] -> 6.05 | BD10: =MacroData[[#This Row],[Labour_Force_Part_Rate]] -> 42.64 | BE10: =MacroData[[#This Row],[Female_LFPR]] -> 48.29 | BF10: =INDEX(MacroData[Male_Wage_Growth], MATCH(Control!A12, MacroData[Year],0)) -> 89.24 | BG10: =INDEX(MacroData[Female_Wage_Growth], MATCH(Control!A12, MacroData[Year],0)) -> 83.52 | BH10: =INDEX(MacroData[Male_Wage_Growth], MATCH(Control!A12, MacroData[Year],0)) - INDEX(MacroData[Female_Wage_Growth], MATCH(Control!A12, MacroData[Year],0)) -> 5.72 | BJ10: =MacroData[[#This Row],[Year]] -> 2007 | BK10: =MacroData[[#This Row],[Exports]] -> 40.39 | BL10: =MacroData[[#This Row],[Imports]] -> 100.88 | BM10: =MacroData[[#This Row],[Exchange_Rate_Movement]] -> 0.51 | BN10: =MacroData[[#This Row],[FDI]] -> 9.22 | BO10: =Table5[[#This Row],[Exports]] - Table5[[#This Row],[Imports]] -> -60.49 | BS10: =MacroData[[#This Row],[Year]] -> 2007 | BT10: =MacroData[[#This Row],[Gov_Expenditure]] -> 34.8 | BU10: =MacroData[[#This Row],[Budget_Deficit]] -> 0.6 | BV10: =MacroData[[#This Row],[Public_Debt]] -> 9 | BW10: =MacroData[[#This Row],[Revenue_Taxation]] -> 26
A11: 2008 | B11: =RIGHT(A11, 2) -> 08 | C11: =$C$28 -> 0.5236 | D11: =GETPIVOTDATA(""&D$1,Control!$W$3,"Year",""&$A11) -> -3.39 | E11: =GETPIVOTDATA(""&E$1,Control!$W$3,"Year",""&$A11) -> -2.04 | F11: =C11 -> 0.5236 | G11: =IFERROR(GETPIVOTDATA(""&D$1,Control!$B$3,"Year",""&$A11),NA()) -> -3.39 | H11: =IFERROR(GETPIVOTDATA(""&E$1,Control!$B$3,"Year",""&$A11),NA()) -> -2.04 | I11: =C11+G11 -> -2.8664 | J11: =IF(G11>1,TEXT(ROUND(G11/1,0),"0"),G11) -> -3.39 | L11: =GETPIVOTDATA(""&L$1,Control!$B$36,"Year",""&$A11) -> 89.88 | M11: =GETPIVOTDATA(""&M$1,Control!$B$36,"Year",""&$A11) -> 84.36 | N11: =L11/SUM(L11:M11) -> 0.51584022 | T11: =GETPIVOTDATA(""&T$1,Control!$B$66,"Year",""&$A11) -> 41.23 | U11: =GETPIVOTDATA(""&U$1,Control!$C$66,"Year",""&$A11) -> 95.77 | V11: =T11/SUM(T11:U11) -> 0.30094891 | AB11: 3.01 | AC11: 20.08 | AD11: 76.01 | AG11: Policy Rate | AH11: =INDEX(MacroData[Policy_Interest_Rate], MATCH(Control!A4, MacroData[Year],0)) -> 5.5 | AJ11: =MacroData[[#This Row],[Year]] -> 2008 | AK11: =MacroData[[#This Row],[Policy_Interest_Rate]] -> 11.4 | AL11: =MacroData[[#This Row],[Market_Interest_Rate]] -> 11.4 | AN11: 2009 | AO11: -5 | AR11: =MacroData[[#This Row],[Year]] -> 2008 | AS11: =MacroData[[#This Row],[Headline_Inflation]] -> 15.04 | AT11: =MacroData[[#This Row],[Core_Inflation]] -> 13.5 | AU11: =MacroData[[#This Row],[Food_Inflation]] -> 19.5 | AV11: =MacroData[[#This Row],[Non_Food_Inflation]] -> 13.1 | AW11: =MacroData[[#This Row],[PPI]] -> 12 | BB11: =MacroData[[#This Row],[Year]] -> 2008 | BC11: =MacroData[[#This Row],[Unemployment_Rate]] -> 7.74 | BD11: =MacroData[[#This Row],[Labour_Force_Part_Rate]] -> 42.87 | BE11: =MacroData[[#This Row],[Female_LFPR]] -> 48.98 | BF11: =INDEX(MacroData[Male_Wage_Growth], MATCH(Control!A13, MacroData[Year],0)) -> 89.28 | BG11: =INDEX(MacroData[Female_Wage_Growth], MATCH(Control!A13, MacroData[Year],0)) -> 83.41 | BH11: =INDEX(MacroData[Male_Wage_Growth], MATCH(Control!A13, MacroData[Year],0)) - INDEX(MacroData[Female_Wage_Growth], MATCH(Control!A13, MacroData[Year],0)) -> 5.87 | BJ11: =MacroData[[#This Row],[Year]] -> 2008 | BK11: =MacroData[[#This Row],[Exports]] -> 41.23 | BL11: =MacroData[[#This Row],[Imports]] -> 95.77 | BM11: =MacroData[[#This Row],[Exchange_Rate_Movement]] -> 0.48 | BN11: =MacroData[[#This Row],[FDI]] -> 4.2 | BO11: =Table5[[#This Row],[Exports]] - Table5[[#This Row],[Imports]] -> -54.54 | BS11: =MacroData[[#This Row],[Year]] -> 2008 | BT11: =MacroData[[#This Row],[Gov_Expenditure]] -> 38.2 | BU11: =MacroData[[#This Row],[Budget_Deficit]] -> -3.3 | BV11: =MacroData[[#This Row],[Public_Debt]] -> 19.3 | BW11: =MacroData[[#This Row],[Revenue_Taxation]] -> 26
A12: 2009 | B12: =RIGHT(A12, 2) -> 09 | C12: =$C$28 -> 0.5236 | D12: =GETPIVOTDATA(""&D$1,Control!$W$3,"Year",""&$A12) -> -16.04 | E12: =GETPIVOTDATA(""&E$1,Control!$W$3,"Year",""&$A12) -> -14.06 | F12: =C12 -> 0.5236 | G12: =IFERROR(GETPIVOTDATA(""&D$1,Control!$B$3,"Year",""&$A12),NA()) -> -16.04 | H12: =IFERROR(GETPIVOTDATA(""&E$1,Control!$B$3,"Year",""&$A12),NA()) -> -14.06 | I12: =C12+G12 -> -15.5164 | J12: =IF(G12>1,TEXT(ROUND(G12/1,0),"0"),G12) -> -16.04 | L12: =GETPIVOTDATA(""&L$1,Control!$B$36,"Year",""&$A12) -> 89.25 | M12: =GETPIVOTDATA(""&M$1,Control!$B$36,"Year",""&$A12) -> 83.54 | N12: =L12/SUM(L12:M12) -> 0.51652295 | T12: =GETPIVOTDATA(""&T$1,Control!$B$66,"Year",""&$A12) -> 43.4 | U12: =GETPIVOTDATA(""&U$1,Control!$C$66,"Year",""&$A12) -> 88.83 | V12: =T12/SUM(T12:U12) -> 0.32821599 | AB12: 3.04 | AC12: 20.02 | AD12: 76.04 | AG12: Money Supply | AH12: =INDEX(MacroData[Money_Supply], MATCH(Control!A4, MacroData[Year],0)) -> 38 | AJ12: =MacroData[[#This Row],[Year]] -> 2009 | AK12: =MacroData[[#This Row],[Policy_Interest_Rate]] -> 14.8 | AL12: =MacroData[[#This Row],[Market_Interest_Rate]] -> 14.8 | AN12: 2010 | AO12: 7 | AR12: =MacroData[[#This Row],[Year]] -> 2009 | AS12: =MacroData[[#This Row],[Headline_Inflation]] -> 3.53 | AT12: =MacroData[[#This Row],[Core_Inflation]] -> 3.8 | AU12: =MacroData[[#This Row],[Food_Inflation]] -> 2.1 | AV12: =MacroData[[#This Row],[Non_Food_Inflation]] -> 1.4 | AW12: =MacroData[[#This Row],[PPI]] -> -3.5 | BB12: =MacroData[[#This Row],[Year]] -> 2009 | BC12: =MacroData[[#This Row],[Unemployment_Rate]] -> 17.52 | BD12: =MacroData[[#This Row],[Labour_Force_Part_Rate]] -> 41.25 | BE12: =MacroData[[#This Row],[Female_LFPR]] -> 49.8 | BF12: =INDEX(MacroData[Male_Wage_Growth], MATCH(Control!A14, MacroData[Year],0)) -> #N/A | BG12: =INDEX(MacroData[Female_Wage_Growth], MATCH(Control!A14, MacroData[Year],0)) -> #N/A | BH12: =INDEX(MacroData[Male_Wage_Growth], MATCH(Control!A14, MacroData[Year],0)) - INDEX(MacroData[Female_Wage_Growth], MATCH(Control!A14, MacroData[Year],0)) -> #N/A | BJ12: =MacroData[[#This Row],[Year]] -> 2009 | BK12: =MacroData[[#This Row],[Exports]] -> 43.4 | BL12: =MacroData[[#This Row],[Imports]] -> 88.83 | BM12: =MacroData[[#This Row],[Exchange_Rate_Movement]] -> 0.51 | BN12: =MacroData[[#This Row],[FDI]] -> -0.58 | BO12: =Table5[[#This Row],[Exports]] - Table5[[#This Row],[Imports]] -> -45.43 | BS12: =MacroData[[#This Row],[Year]] -> 2009 | BT12: =MacroData[[#This Row],[Gov_Expenditure]] -> 43.6 | BU12: =MacroData[[#This Row],[Budget_Deficit]] -> -7.1 | BV12: =MacroData[[#This Row],[Public_Debt]] -> 37.6 | BW12: =MacroData[[#This Row],[Revenue_Taxation]] -> 24
A13: 2010 | B13: =RIGHT(A13, 2) -> 10 | C13: =$C$28 -> 0.5236 | D13: =GETPIVOTDATA(""&D$1,Control!$W$3,"Year",""&$A13) -> -3.66 | E13: =GETPIVOTDATA(""&E$1,Control!$W$3,"Year",""&$A13) -> -1.06 | F13: =C13 -> 0.5236 | G13: =IFERROR(GETPIVOTDATA(""&D$1,Control!$B$3,"Year",""&$A13),NA()) -> -3.66 | H13: =IFERROR(GETPIVOTDATA(""&E$1,Control!$B$3,"Year",""&$A13),NA()) -> -1.06 | I13: =C13+G13 -> -3.1364 | J13: =IF(G13>1,TEXT(ROUND(G13/1,0),"0"),G13) -> -3.66 | L13: =GETPIVOTDATA(""&L$1,Control!$B$36,"Year",""&$A13) -> 88.88 | M13: =GETPIVOTDATA(""&M$1,Control!$B$36,"Year",""&$A13) -> 83.57 | N13: =L13/SUM(L13:M13) -> 0.51539577 | T13: =GETPIVOTDATA(""&T$1,Control!$B$66,"Year",""&$A13) -> 54.37 | U13: =GETPIVOTDATA(""&U$1,Control!$C$66,"Year",""&$A13) -> 110.86 | V13: =T13/SUM(T13:U13) -> 0.32905647 | AB13: 4.01 | AC13: 22.06 | AD13: 73.03 | AG13: Credit Growth | AH13: =INDEX(MacroData[Credit_Growth], MATCH(Control!A4, MacroData[Year],0)) -> 62.7 | AJ13: =MacroData[[#This Row],[Year]] -> 2010 | AK13: =MacroData[[#This Row],[Policy_Interest_Rate]] -> 9.2 | AL13: =MacroData[[#This Row],[Market_Interest_Rate]] -> 9.2 | AN13: 2011 | AO13: 2 | AR13: =MacroData[[#This Row],[Year]] -> 2010 | AS13: =MacroData[[#This Row],[Headline_Inflation]] -> -1.08 | AT13: =MacroData[[#This Row],[Core_Inflation]] -> -2.5 | AU13: =MacroData[[#This Row],[Food_Inflation]] -> 1 | AV13: =MacroData[[#This Row],[Non_Food_Inflation]] -> -2.2 | AW13: =MacroData[[#This Row],[PPI]] -> 1.4 | BB13: =MacroData[[#This Row],[Year]] -> 2010 | BC13: =MacroData[[#This Row],[Unemployment_Rate]] -> 19.48 | BD13: =MacroData[[#This Row],[Labour_Force_Part_Rate]] -> 39.75 | BE13: =MacroData[[#This Row],[Female_LFPR]] -> 50.39 | BF13: =INDEX(MacroData[Male_Wage_Growth], MATCH(Control!A15, MacroData[Year],0)) -> #N/A | BG13: =INDEX(MacroData[Female_Wage_Growth], MATCH(Control!A15, MacroData[Year],0)) -> #N/A | BH13: =INDEX(MacroData[Male_Wage_Growth], MATCH(Control!A15, MacroData[Year],0)) - INDEX(MacroData[Female_Wage_Growth], MATCH(Control!A15, MacroData[Year],0)) -> #N/A | BJ13: =MacroData[[#This Row],[Year]] -> 2010 | BK13: =MacroData[[#This Row],[Exports]] -> 54.37 | BL13: =MacroData[[#This Row],[Imports]] -> 110.86 | BM13: =MacroData[[#This Row],[Exchange_Rate_Movement]] -> 0.53 | BN13: =MacroData[[#This Row],[FDI]] -> 2.02 | BO13: =Table5[[#This Row],[Exports]] - Table5[[#This Row],[Imports]] -> -56.49 | BS13: =MacroData[[#This Row],[Year]] -> 2010 | BT13: =MacroData[[#This Row],[Gov_Expenditure]] -> 43.6 | BU13: =MacroData[[#This Row],[Budget_Deficit]] -> -6.6 | BV13: =MacroData[[#This Row],[Public_Debt]] -> 48.2 | BW13: =MacroData[[#This Row],[Revenue_Taxation]] -> 23
A14: 2011 | B14: =RIGHT(A14, 2) -> 11 | C14: =$C$28 -> 0.5236 | D14: =GETPIVOTDATA(""&D$1,Control!$W$3,"Year",""&$A14) -> 3.04 | E14: =GETPIVOTDATA(""&E$1,Control!$W$3,"Year",""&$A14) -> 4.09 | F14: =C14 -> 0.5236 | G14: =IFERROR(GETPIVOTDATA(""&D$1,Control!$B$3,"Year",""&$A14),NA()) -> 3.04 | H14: =IFERROR(GETPIVOTDATA(""&E$1,Control!$B$3,"Year",""&$A14),NA()) -> 4.09 | I14: =C14+G14 -> 3.5636 | J14: =IF(G14>1,TEXT(ROUND(G14/1,0),"0"),G14) -> 3 | L14: =GETPIVOTDATA(""&L$1,Control!$B$36,"Year",""&$A14) -> 89.02 | M14: =GETPIVOTDATA(""&M$1,Control!$B$36,"Year",""&$A14) -> 83.66 | N14: =L14/SUM(L14:M14) -> 0.51552004 | T14: =GETPIVOTDATA(""&T$1,Control!$B$66,"Year",""&$A14) -> 61.8 | U14: =GETPIVOTDATA(""&U$1,Control!$C$66,"Year",""&$A14) -> 129.73 | V14: =T14/SUM(T14:U14) -> 0.32266486 | AB14: 4.03 | AC14: 24 | AD14: 71.07 | AJ14: =MacroData[[#This Row],[Year]] -> 2011 | AK14: =MacroData[[#This Row],[Policy_Interest_Rate]] -> 6.4 | AL14: =MacroData[[#This Row],[Market_Interest_Rate]] -> 6.4 | AN14: 2012 | AO14: 6 | AR14: =MacroData[[#This Row],[Year]] -> 2011 | AS14: =MacroData[[#This Row],[Headline_Inflation]] -> 4.37 | AT14: =MacroData[[#This Row],[Core_Inflation]] -> 2.6 | AU14: =MacroData[[#This Row],[Food_Inflation]] -> 7.9 | AV14: =MacroData[[#This Row],[Non_Food_Inflation]] -> 4.1 | AW14: =MacroData[[#This Row],[PPI]] -> 8.2 | BB14: =MacroData[[#This Row],[Year]] -> 2011 | BC14: =MacroData[[#This Row],[Unemployment_Rate]] -> 16.21 | BD14: =MacroData[[#This Row],[Labour_Force_Part_Rate]] -> 37.48 | BE14: =MacroData[[#This Row],[Female_LFPR]] -> 49.94 | BF14: =INDEX(MacroData[Male_Wage_Growth], MATCH(Control!A16, MacroData[Year],0)) -> #N/A | BG14: =INDEX(MacroData[Female_Wage_Growth], MATCH(Control!A16, MacroData[Year],0)) -> #N/A | BH14: =INDEX(MacroData[Male_Wage_Growth], MATCH(Control!A16, MacroData[Year],0)) - INDEX(MacroData[Female_Wage_Growth], MATCH(Control!A16, MacroData[Year],0)) -> #N/A | BJ14: =MacroData[[#This Row],[Year]] -> 2011 | BK14: =MacroData[[#This Row],[Exports]] -> 61.8 | BL14: =MacroData[[#This Row],[Imports]] -> 129.73 | BM14: =MacroData[[#This Row],[Exchange_Rate_Movement]] -> 0.51 | BN14: =MacroData[[#This Row],[FDI]] -> 5.72 | BO14: =Table5[[#This Row],[Exports]] - Table5[[#This Row],[Imports]] -> -67.93 | BS14: =MacroData[[#This Row],[Year]] -> 2011 | BT14: =MacroData[[#This Row],[Gov_Expenditure]] -> 41.2 | BU14: =MacroData[[#This Row],[Budget_Deficit]] -> -3.4 | BV14: =MacroData[[#This Row],[Public_Debt]] -> 46.8 | BW14: =MacroData[[#This Row],[Revenue_Taxation]] -> 24
A15: 2012 | B15: =RIGHT(A15, 2) -> 12 | C15: =$C$28 -> 0.5236 | D15: =GETPIVOTDATA(""&D$1,Control!$W$3,"Year",""&$A15) -> 7.31 | E15: =GETPIVOTDATA(""&E$1,Control!$W$3,"Year",""&$A15) -> 8.06 | F15: =C15 -> 0.5236 | G15: =IFERROR(GETPIVOTDATA(""&D$1,Control!$B$3,"Year",""&$A15),NA()) -> 7.31 | H15: =IFERROR(GETPIVOTDATA(""&E$1,Control!$B$3,"Year",""&$A15),NA()) -> 8.06 | I15: =C15+G15 -> 7.8336 | J15: =IF(G15>1,TEXT(ROUND(G15/1,0),"0"),G15) -> 7 | L15: =GETPIVOTDATA(""&L$1,Control!$B$36,"Year",""&$A15) -> 89.27 | M15: =GETPIVOTDATA(""&M$1,Control!$B$36,"Year",""&$A15) -> 83.62 | N15: =L15/SUM(L15:M15) -> 0.51633987 | T15: =GETPIVOTDATA(""&T$1,Control!$B$66,"Year",""&$A15) -> 63.83 | U15: =GETPIVOTDATA(""&U$1,Control!$C$66,"Year",""&$A15) -> 133.21 | V15: =T15/SUM(T15:U15) -> 0.32394438 | AB15: 4.05 | AC15: 24.03 | AD15: 71.02 | AJ15: =MacroData[[#This Row],[Year]] -> 2012 | AK15: =MacroData[[#This Row],[Policy_Interest_Rate]] -> 5.1 | AL15: =MacroData[[#This Row],[Market_Interest_Rate]] -> 5.1 | AN15: 2013 | AO15: 13 | AR15: =MacroData[[#This Row],[Year]] -> 2012 | AS15: =MacroData[[#This Row],[Headline_Inflation]] -> 2.26 | AT15: =MacroData[[#This Row],[Core_Inflation]] -> 1.6 | AU15: =MacroData[[#This Row],[Food_Inflation]] -> 2.2 | AV15: =MacroData[[#This Row],[Non_Food_Inflation]] -> 2.5 | AW15: =MacroData[[#This Row],[PPI]] -> 3.8 | BB15: =MacroData[[#This Row],[Year]] -> 2012 | BC15: =MacroData[[#This Row],[Unemployment_Rate]] -> 15.05 | BD15: =MacroData[[#This Row],[Labour_Force_Part_Rate]] -> 40.15 | BE15: =MacroData[[#This Row],[Female_LFPR]] -> 50.01 | BF15: =INDEX(MacroData[Male_Wage_Growth], MATCH(Control!A17, MacroData[Year],0)) -> #N/A | BG15: =INDEX(MacroData[Female_Wage_Growth], MATCH(Control!A17, MacroData[Year],0)) -> #N/A | BH15: =INDEX(MacroData[Male_Wage_Growth], MATCH(Control!A17, MacroData[Year],0)) - INDEX(MacroData[Female_Wage_Growth], MATCH(Control!A17, MacroData[Year],0)) -> #N/A | BJ15: =MacroData[[#This Row],[Year]] -> 2012 | BK15: =MacroData[[#This Row],[Exports]] -> 63.83 | BL15: =MacroData[[#This Row],[Imports]] -> 133.21 | BM15: =MacroData[[#This Row],[Exchange_Rate_Movement]] -> 0.54 | BN15: =MacroData[[#This Row],[FDI]] -> 3.99 | BO15: =Table5[[#This Row],[Exports]] - Table5[[#This Row],[Imports]] -> -69.38 | BS15: =MacroData[[#This Row],[Year]] -> 2012 | BT15: =MacroData[[#This Row],[Gov_Expenditure]] -> 38.6 | BU15: =MacroData[[#This Row],[Budget_Deficit]] -> 0.2 | BV15: =MacroData[[#This Row],[Public_Debt]] -> 44.4 | BW15: =MacroData[[#This Row],[Revenue_Taxation]] -> 24
A16: 2013 | B16: =RIGHT(A16, 2) -> 13 | C16: =$C$28 -> 0.5236 | D16: =GETPIVOTDATA(""&D$1,Control!$W$3,"Year",""&$A16) -> 2.01 | E16: =GETPIVOTDATA(""&E$1,Control!$W$3,"Year",""&$A16) -> 3.02 | F16: =C16 -> 0.5236 | G16: =IFERROR(GETPIVOTDATA(""&D$1,Control!$B$3,"Year",""&$A16),NA()) -> 2.01 | H16: =IFERROR(GETPIVOTDATA(""&E$1,Control!$B$3,"Year",""&$A16),NA()) -> 3.02 | I16: =C16+G16 -> 2.5336 | J16: =IF(G16>1,TEXT(ROUND(G16/1,0),"0"),G16) -> 2 | L16: =GETPIVOTDATA(""&L$1,Control!$B$36,"Year",""&$A16) -> 89.24 | M16: =GETPIVOTDATA(""&M$1,Control!$B$36,"Year",""&$A16) -> 83.52 | N16: =L16/SUM(L16:M16) -> 0.51655476 | T16: =GETPIVOTDATA(""&T$1,Control!$B$66,"Year",""&$A16) -> 62.58 | U16: =GETPIVOTDATA(""&U$1,Control!$C$66,"Year",""&$A16) -> 129.68 | V16: =T16/SUM(T16:U16) -> 0.32549672 | AB16: 4.01 | AC16: 23.08 | AD16: 72.01 | AJ16: =MacroData[[#This Row],[Year]] -> 2013 | AK16: =MacroData[[#This Row],[Policy_Interest_Rate]] -> 4.3 | AL16: =MacroData[[#This Row],[Market_Interest_Rate]] -> 4.3 | AN16: 2014 | AO16: 8.02 | AR16: =MacroData[[#This Row],[Year]] -> 2013 | AS16: =MacroData[[#This Row],[Headline_Inflation]] -> -0.03 | AT16: =MacroData[[#This Row],[Core_Inflation]] -> 0.3 | AU16: =MacroData[[#This Row],[Food_Inflation]] -> 1.2 | AV16: =MacroData[[#This Row],[Non_Food_Inflation]] -> -1.1 | AW16: =MacroData[[#This Row],[PPI]] -> 0.7 | BB16: =MacroData[[#This Row],[Year]] -> 2013 | BC16: =MacroData[[#This Row],[Unemployment_Rate]] -> 11.87 | BD16: =MacroData[[#This Row],[Labour_Force_Part_Rate]] -> 39.37 | BE16: =MacroData[[#This Row],[Female_LFPR]] -> 49.99 | BF16: =INDEX(MacroData[Male_Wage_Growth], MATCH(Control!A18, MacroData[Year],0)) -> #N/A | BG16: =INDEX(MacroData[Female_Wage_Growth], MATCH(Control!A18, MacroData[Year],0)) -> #N/A | BH16: =INDEX(MacroData[Male_Wage_Growth], MATCH(Control!A18, MacroData[Year],0)) - INDEX(MacroData[Female_Wage_Growth], MATCH(Control!A18, MacroData[Year],0)) -> #N/A | BJ16: =MacroData[[#This Row],[Year]] -> 2013 | BK16: =MacroData[[#This Row],[Exports]] -> 62.58 | BL16: =MacroData[[#This Row],[Imports]] -> 129.68 | BM16: =MacroData[[#This Row],[Exchange_Rate_Movement]] -> 0.53 | BN16: =MacroData[[#This Row],[FDI]] -> 3.39 | BO16: =Table5[[#This Row],[Exports]] - Table5[[#This Row],[Imports]] -> -67.1 | BS16: =MacroData[[#This Row],[Year]] -> 2013 | BT16: =MacroData[[#This Row],[Gov_Expenditure]] -> 38.7 | BU16: =MacroData[[#This Row],[Budget_Deficit]] -> -0.6 | BV16: =MacroData[[#This Row],[Public_Debt]] -> 41.8 | BW16: =MacroData[[#This Row],[Revenue_Taxation]] -> 25
A17: 2014 | B17: =RIGHT(A17, 2) -> 14 | C17: =$C$28 -> 0.5236 | D17: =GETPIVOTDATA(""&D$1,Control!$W$3,"Year",""&$A17) -> 2.09 | E17: =GETPIVOTDATA(""&E$1,Control!$W$3,"Year",""&$A17) -> 3.01 | F17: =C17 -> 0.5236 | G17: =IFERROR(GETPIVOTDATA(""&D$1,Control!$B$3,"Year",""&$A17),NA()) -> 2.09 | H17: =IFERROR(GETPIVOTDATA(""&E$1,Control!$B$3,"Year",""&$A17),NA()) -> 3.01 | I17: =C17+G17 -> 2.6136 | J17: =IF(G17>1,TEXT(ROUND(G17/1,0),"0"),G17) -> 2 | L17: =GETPIVOTDATA(""&L$1,Control!$B$36,"Year",""&$A17) -> 89.28 | M17: =GETPIVOTDATA(""&M$1,Control!$B$36,"Year",""&$A17) -> 83.41 | N17: =L17/SUM(L17:M17) -> 0.51699577 | T17: =GETPIVOTDATA(""&T$1,Control!$B$66,"Year",""&$A17) -> 63.57 | U17: =GETPIVOTDATA(""&U$1,Control!$C$66,"Year",""&$A17) -> 130.04 | V17: =T17/SUM(T17:U17) -> 0.32834048 | AB17: 3.07 | AC17: 23.04 | AD17: 72.09 | AJ17: =MacroData[[#This Row],[Year]] -> 2014 | AK17: =MacroData[[#This Row],[Policy_Interest_Rate]] -> 3.8 | AL17: =MacroData[[#This Row],[Market_Interest_Rate]] -> 3.8 | AN17: 2015 | AO17: 8.04 | AR17: =MacroData[[#This Row],[Year]] -> 2014 | AS17: =MacroData[[#This Row],[Headline_Inflation]] -> 0.62 | AT17: =MacroData[[#This Row],[Core_Inflation]] -> 0.9 | AU17: =MacroData[[#This Row],[Food_Inflation]] -> 0.4 | AV17: =MacroData[[#This Row],[Non_Food_Inflation]] -> 0.8 | AW17: =MacroData[[#This Row],[PPI]] -> -0.3 | BB17: =MacroData[[#This Row],[Year]] -> 2014 | BC17: =MacroData[[#This Row],[Unemployment_Rate]] -> 10.85 | BD17: =MacroData[[#This Row],[Labour_Force_Part_Rate]] -> 40.43 | BE17: =MacroData[[#This Row],[Female_LFPR]] -> 49.59 | BF17: =INDEX(MacroData[Male_Wage_Growth], MATCH(Control!A19, MacroData[Year],0)) -> #N/A | BG17: =INDEX(MacroData[Female_Wage_Growth], MATCH(Control!A19, MacroData[Year],0)) -> #N/A | BH17: =INDEX(MacroData[Male_Wage_Growth], MATCH(Control!A19, MacroData[Year],0)) - INDEX(MacroData[Female_Wage_Growth], MATCH(Control!A19, MacroData[Year],0)) -> #N/A | BJ17: =MacroData[[#This Row],[Year]] -> 2014 | BK17: =MacroData[[#This Row],[Exports]] -> 63.57 | BL17: =MacroData[[#This Row],[Imports]] -> 130.04 | BM17: =MacroData[[#This Row],[Exchange_Rate_Movement]] -> 0.75 | BN17: =MacroData[[#This Row],[FDI]] -> 3.45 | BO17: =Table5[[#This Row],[Exports]] - Table5[[#This Row],[Imports]] -> -66.47 | BS17: =MacroData[[#This Row],[Year]] -> 2014 | BT17: =MacroData[[#This Row],[Gov_Expenditure]] -> 39.2 | BU17: =MacroData[[#This Row],[Budget_Deficit]] -> -1.7 | BV17: =MacroData[[#This Row],[Public_Debt]] -> 43.1 | BW17: =MacroData[[#This Row],[Revenue_Taxation]] -> 26
A18: 2015 | B18: =RIGHT(A18, 2) -> 15 | C18: =$C$28 -> 0.5236 | D18: =GETPIVOTDATA(""&D$1,Control!$W$3,"Year",""&$A18) -> 3.78 | E18: =GETPIVOTDATA(""&E$1,Control!$W$3,"Year",""&$A18) -> 4.06 | F18: =C18 -> 0.5236 | G18: =IFERROR(GETPIVOTDATA(""&D$1,Control!$B$3,"Year",""&$A18),NA()) -> #N/A | H18: =IFERROR(GETPIVOTDATA(""&E$1,Control!$B$3,"Year",""&$A18),NA()) -> #N/A | I18: =C18+G18 -> #N/A | J18: =IF(G18>1,TEXT(ROUND(G18/1,0),"0"),G18) -> #N/A | L18: =GETPIVOTDATA(""&L$1,Control!$B$36,"Year",""&$A18) -> 89.15 | M18: =GETPIVOTDATA(""&M$1,Control!$B$36,"Year",""&$A18) -> 83.18 | N18: =L18/SUM(L18:M18) -> 0.51732142 | T18: =GETPIVOTDATA(""&T$1,Control!$B$66,"Year",""&$A18) -> 62.6 | U18: =GETPIVOTDATA(""&U$1,Control!$C$66,"Year",""&$A18) -> 126.38 | V18: =T18/SUM(T18:U18) -> 0.33125198 | AB18: 3.09 | AC18: 23.03 | AD18: 72.08 | AJ18: =MacroData[[#This Row],[Year]] -> 2015 | AK18: =MacroData[[#This Row],[Policy_Interest_Rate]] -> 3.5 | AL18: =MacroData[[#This Row],[Market_Interest_Rate]] -> 3.5 | AN18: 2016 | AO18: 6.08 | AR18: =MacroData[[#This Row],[Year]] -> 2015 | AS18: =MacroData[[#This Row],[Headline_Inflation]] -> 0.17 | AT18: =MacroData[[#This Row],[Core_Inflation]] -> 1.2 | AU18: =MacroData[[#This Row],[Food_Inflation]] -> -0.3 | AV18: =MacroData[[#This Row],[Non_Food_Inflation]] -> -0.1 | AW18: =MacroData[[#This Row],[PPI]] -> -1.1 | BB18: =MacroData[[#This Row],[Year]] -> 2015 | BC18: =MacroData[[#This Row],[Unemployment_Rate]] -> 9.87 | BD18: =MacroData[[#This Row],[Labour_Force_Part_Rate]] -> 41.29 | BE18: =MacroData[[#This Row],[Female_LFPR]] -> 49.56 | BF18: =INDEX(MacroData[Male_Wage_Growth], MATCH(Control!A20, MacroData[Year],0)) -> #N/A | BG18: =INDEX(MacroData[Female_Wage_Growth], MATCH(Control!A20, MacroData[Year],0)) -> #N/A | BH18: =INDEX(MacroData[Male_Wage_Growth], MATCH(Control!A20, MacroData[Year],0)) - INDEX(MacroData[Female_Wage_Growth], MATCH(Control!A20, MacroData[Year],0)) -> #N/A | BJ18: =MacroData[[#This Row],[Year]] -> 2015 | BK18: =MacroData[[#This Row],[Exports]] -> 62.6 | BL18: =MacroData[[#This Row],[Imports]] -> 126.38 | BM18: =MacroData[[#This Row],[Exchange_Rate_Movement]] -> 0.91 | BN18: =MacroData[[#This Row],[FDI]] -> 3.09 | BO18: =Table5[[#This Row],[Exports]] - Table5[[#This Row],[Imports]] -> -63.78 | BS18: =MacroData[[#This Row],[Year]] -> 2015 | BT18: =MacroData[[#This Row],[Gov_Expenditure]] -> 38.7 | BU18: =MacroData[[#This Row],[Budget_Deficit]] -> -1.6 | BV18: =MacroData[[#This Row],[Public_Debt]] -> 38.3 | BW18: =MacroData[[#This Row],[Revenue_Taxation]] -> 26
A19: 2016 | B19: =RIGHT(A19, 2) -> 16 | C19: =$C$28 -> 0.5236 | D19: =GETPIVOTDATA(""&D$1,Control!$W$3,"Year",""&$A19) -> 2.55 | E19: =GETPIVOTDATA(""&E$1,Control!$W$3,"Year",""&$A19) -> 3.05 | F19: =C19 -> 0.5236 | G19: =IFERROR(GETPIVOTDATA(""&D$1,Control!$B$3,"Year",""&$A19),NA()) -> #N/A | H19: =IFERROR(GETPIVOTDATA(""&E$1,Control!$B$3,"Year",""&$A19),NA()) -> #N/A | I19: =C19+G19 -> #N/A | J19: =IF(G19>1,TEXT(ROUND(G19/1,0),"0"),G19) -> #N/A | L19: =GETPIVOTDATA(""&L$1,Control!$B$36,"Year",""&$A19) -> 89 | M19: =GETPIVOTDATA(""&M$1,Control!$B$36,"Year",""&$A19) -> 83.07 | N19: =L19/SUM(L19:M19) -> 0.51723136 | T19: =GETPIVOTDATA(""&T$1,Control!$B$66,"Year",""&$A19) -> 61.93 | U19: =GETPIVOTDATA(""&U$1,Control!$C$66,"Year",""&$A19) -> 123.33 | V19: =T19/SUM(T19:U19) -> 0.33428695 | AB19: 3.09 | AC19: 24.01 | AD19: 72 | AJ19: =MacroData[[#This Row],[Year]] -> 2016 | AK19: =MacroData[[#This Row],[Policy_Interest_Rate]] -> 3.2 | AL19: =MacroData[[#This Row],[Market_Interest_Rate]] -> 3.2 | AN19: 2017 | AO19: 3.02 | AR19: =MacroData[[#This Row],[Year]] -> 2016 | AS19: =MacroData[[#This Row],[Headline_Inflation]] -> 0.14 | AT19: =MacroData[[#This Row],[Core_Inflation]] -> 1 | AU19: =MacroData[[#This Row],[Food_Inflation]] -> -0.7 | AV19: =MacroData[[#This Row],[Non_Food_Inflation]] -> -0.6 | AW19: =MacroData[[#This Row],[PPI]] -> -1.7 | BB19: =MacroData[[#This Row],[Year]] -> 2016 | BC19: =MacroData[[#This Row],[Unemployment_Rate]] -> 9.64 | BD19: =MacroData[[#This Row],[Labour_Force_Part_Rate]] -> 39.7 | BE19: =MacroData[[#This Row],[Female_LFPR]] -> 50.08 | BF19: =INDEX(MacroData[Male_Wage_Growth], MATCH(Control!A21, MacroData[Year],0)) -> #N/A | BG19: =INDEX(MacroData[Female_Wage_Growth], MATCH(Control!A21, MacroData[Year],0)) -> #N/A | BH19: =INDEX(MacroData[Male_Wage_Growth], MATCH(Control!A21, MacroData[Year],0)) - INDEX(MacroData[Female_Wage_Growth], MATCH(Control!A21, MacroData[Year],0)) -> #N/A | BJ19: =MacroData[[#This Row],[Year]] -> 2016 | BK19: =MacroData[[#This Row],[Exports]] -> 61.93 | BL19: =MacroData[[#This Row],[Imports]] -> 123.33 | BM19: =MacroData[[#This Row],[Exchange_Rate_Movement]] -> 0.91 | BN19: =MacroData[[#This Row],[FDI]] -> 1.24 | BO19: =Table5[[#This Row],[Exports]] - Table5[[#This Row],[Imports]] -> -61.4 | BS19: =MacroData[[#This Row],[Year]] -> 2016 | BT19: =MacroData[[#This Row],[Gov_Expenditure]] -> 37.4 | BU19: =MacroData[[#This Row],[Budget_Deficit]] -> -0.5 | BV19: =MacroData[[#This Row],[Public_Debt]] -> 41.7 | BW19: =MacroData[[#This Row],[Revenue_Taxation]] -> 27
A20: 2017 | B20: =RIGHT(A20, 2) -> 17 | C20: =$C$28 -> 0.5236 | D20: =GETPIVOTDATA(""&D$1,Control!$W$3,"Year",""&$A20) -> 3.04 | E20: =GETPIVOTDATA(""&E$1,Control!$W$3,"Year",""&$A20) -> 4.03 | F20: =C20 -> 0.5236 | G20: =IFERROR(GETPIVOTDATA(""&D$1,Control!$B$3,"Year",""&$A20),NA()) -> #N/A | H20: =IFERROR(GETPIVOTDATA(""&E$1,Control!$B$3,"Year",""&$A20),NA()) -> #N/A | I20: =C20+G20 -> #N/A | J20: =IF(G20>1,TEXT(ROUND(G20/1,0),"0"),G20) -> #N/A | L20: =GETPIVOTDATA(""&L$1,Control!$B$36,"Year",""&$A20) -> 89.47 | M20: =GETPIVOTDATA(""&M$1,Control!$B$36,"Year",""&$A20) -> 84.05 | N20: =L20/SUM(L20:M20) -> 0.5156178 | T20: =GETPIVOTDATA(""&T$1,Control!$B$66,"Year",""&$A20) -> 64.14 | U20: =GETPIVOTDATA(""&U$1,Control!$C$66,"Year",""&$A20) -> 128.71 | V20: =T20/SUM(T20:U20) -> 0.3325901 | AB20: 3.09 | AC20: 22.04 | AD20: 73.07 | AJ20: =MacroData[[#This Row],[Year]] -> 2017 | AK20: =MacroData[[#This Row],[Policy_Interest_Rate]] -> 2.9 | AL20: =MacroData[[#This Row],[Market_Interest_Rate]] -> 2.9 | AN20: 2018 | AO20: 13.08 | AR20: =MacroData[[#This Row],[Year]] -> 2017 | AS20: =MacroData[[#This Row],[Headline_Inflation]] -> 2.93 | AT20: =MacroData[[#This Row],[Core_Inflation]] -> 1.9 | AU20: =MacroData[[#This Row],[Food_Inflation]] -> 4.9 | AV20: =MacroData[[#This Row],[Non_Food_Inflation]] -> 2.2 | AW20: =MacroData[[#This Row],[PPI]] -> 3.2 | BB20: =MacroData[[#This Row],[Year]] -> 2017 | BC20: =MacroData[[#This Row],[Unemployment_Rate]] -> 8.72 | BD20: =MacroData[[#This Row],[Labour_Force_Part_Rate]] -> 39.76 | BE20: =MacroData[[#This Row],[Female_LFPR]] -> 49.89 | BF20: =INDEX(MacroData[Male_Wage_Growth], MATCH(Control!A22, MacroData[Year],0)) -> #N/A | BG20: =INDEX(MacroData[Female_Wage_Growth], MATCH(Control!A22, MacroData[Year],0)) -> #N/A | BH20: =INDEX(MacroData[Male_Wage_Growth], MATCH(Control!A22, MacroData[Year],0)) - INDEX(MacroData[Female_Wage_Growth], MATCH(Control!A22, MacroData[Year],0)) -> #N/A | BJ20: =MacroData[[#This Row],[Year]] -> 2017 | BK20: =MacroData[[#This Row],[Exports]] -> 64.14 | BL20: =MacroData[[#This Row],[Imports]] -> 128.71 | BM20: =MacroData[[#This Row],[Exchange_Rate_Movement]] -> 0.88 | BN20: =MacroData[[#This Row],[FDI]] -> 4.05 | BO20: =Table5[[#This Row],[Exports]] - Table5[[#This Row],[Imports]] -> -64.57 | BS20: =MacroData[[#This Row],[Year]] -> 2017 | BT20: =MacroData[[#This Row],[Gov_Expenditure]] -> 37.8 | BU20: =MacroData[[#This Row],[Budget_Deficit]] -> -0.9 | BV20: =MacroData[[#This Row],[Public_Debt]] -> 40.3 | BW20: =MacroData[[#This Row],[Revenue_Taxation]] -> 28
A21: 2018 | B21: =RIGHT(A21, 2) -> 18 | C21: =$C$28 -> 0.5236 | D21: =GETPIVOTDATA(""&D$1,Control!$W$3,"Year",""&$A21) -> 4.31 | E21: =GETPIVOTDATA(""&E$1,Control!$W$3,"Year",""&$A21) -> 5.01 | F21: =C21 -> 0.5236 | G21: =IFERROR(GETPIVOTDATA(""&D$1,Control!$B$3,"Year",""&$A21),NA()) -> #N/A | H21: =IFERROR(GETPIVOTDATA(""&E$1,Control!$B$3,"Year",""&$A21),NA()) -> #N/A | I21: =C21+G21 -> #N/A | J21: =IF(G21>1,TEXT(ROUND(G21/1,0),"0"),G21) -> #N/A | L21: =GETPIVOTDATA(""&L$1,Control!$B$36,"Year",""&$A21) -> 89.58 | M21: =GETPIVOTDATA(""&M$1,Control!$B$36,"Year",""&$A21) -> 83.97 | N21: =L21/SUM(L21:M21) -> 0.51616249 | T21: =GETPIVOTDATA(""&T$1,Control!$B$66,"Year",""&$A21) -> 63.87 | U21: =GETPIVOTDATA(""&U$1,Control!$C$66,"Year",""&$A21) -> 128.23 | V21: =T21/SUM(T21:U21) -> 0.33248308 | AB21: 3.07 | AC21: 22.09 | AD21: 73.04 | AJ21: =MacroData[[#This Row],[Year]] -> 2018 | AK21: =MacroData[[#This Row],[Policy_Interest_Rate]] -> 2.8 | AL21: =MacroData[[#This Row],[Market_Interest_Rate]] -> 2.8 | AN21: 2019 | AO21: 8 | AR21: =MacroData[[#This Row],[Year]] -> 2018 | AS21: =MacroData[[#This Row],[Headline_Inflation]] -> 2.53 | AT21: =MacroData[[#This Row],[Core_Inflation]] -> 2 | AU21: =MacroData[[#This Row],[Food_Inflation]] -> 1.3 | AV21: =MacroData[[#This Row],[Non_Food_Inflation]] -> 3.1 | AW21: =MacroData[[#This Row],[PPI]] -> 4.3 | BB21: =MacroData[[#This Row],[Year]] -> 2018 | BC21: =MacroData[[#This Row],[Unemployment_Rate]] -> 7.41 | BD21: =MacroData[[#This Row],[Labour_Force_Part_Rate]] -> 37.73 | BE21: =MacroData[[#This Row],[Female_LFPR]] -> 49.89 | BF21: =INDEX(MacroData[Male_Wage_Growth], MATCH(Control!A23, MacroData[Year],0)) -> #N/A | BG21: =INDEX(MacroData[Female_Wage_Growth], MATCH(Control!A23, MacroData[Year],0)) -> #N/A | BH21: =INDEX(MacroData[Male_Wage_Growth], MATCH(Control!A23, MacroData[Year],0)) - INDEX(MacroData[Female_Wage_Growth], MATCH(Control!A23, MacroData[Year],0)) -> #N/A | BJ21: =MacroData[[#This Row],[Year]] -> 2018 | BK21: =MacroData[[#This Row],[Exports]] -> 63.87 | BL21: =MacroData[[#This Row],[Imports]] -> 128.23 | BM21: =MacroData[[#This Row],[Exchange_Rate_Movement]] -> 0.85 | BN21: =MacroData[[#This Row],[FDI]] -> 1.32 | BO21: =Table5[[#This Row],[Exports]] - Table5[[#This Row],[Imports]] -> -64.36 | BS21: =MacroData[[#This Row],[Year]] -> 2018 | BT21: =MacroData[[#This Row],[Gov_Expenditure]] -> 39.4 | BU21: =MacroData[[#This Row],[Budget_Deficit]] -> -0.8 | BV21: =MacroData[[#This Row],[Public_Debt]] -> 38.3 | BW21: =MacroData[[#This Row],[Revenue_Taxation]] -> 28
A22: 2019 | B22: =RIGHT(A22, 2) -> 19 | C22: =$C$28 -> 0.5236 | D22: =GETPIVOTDATA(""&D$1,Control!$W$3,"Year",""&$A22) -> 0.68 | E22: =GETPIVOTDATA(""&E$1,Control!$W$3,"Year",""&$A22) -> 1.04 | F22: =C22 -> 0.5236 | G22: =IFERROR(GETPIVOTDATA(""&D$1,Control!$B$3,"Year",""&$A22),NA()) -> #N/A | H22: =IFERROR(GETPIVOTDATA(""&E$1,Control!$B$3,"Year",""&$A22),NA()) -> #N/A | I22: =C22+G22 -> #N/A | J22: =IF(G22>1,TEXT(ROUND(G22/1,0),"0"),G22) -> #N/A | L22: =GETPIVOTDATA(""&L$1,Control!$B$36,"Year",""&$A22) -> 89.61 | M22: =GETPIVOTDATA(""&M$1,Control!$B$36,"Year",""&$A22) -> 84.35 | N22: =L22/SUM(L22:M22) -> 0.51511842 | T22: =GETPIVOTDATA(""&T$1,Control!$B$66,"Year",""&$A22) -> 62.54 | U22: =GETPIVOTDATA(""&U$1,Control!$C$66,"Year",""&$A22) -> 125.29 | V22: =T22/SUM(T22:U22) -> 0.33296066 | AB22: 3.09 | AC22: 22.01 | AD22: 74 | AJ22: =MacroData[[#This Row],[Year]] -> 2019 | AK22: =MacroData[[#This Row],[Policy_Interest_Rate]] -> 2.9 | AL22: =MacroData[[#This Row],[Market_Interest_Rate]] -> 2.9 | AN22: 2020 | AO22: 13.01 | AR22: =MacroData[[#This Row],[Year]] -> 2019 | AS22: =MacroData[[#This Row],[Headline_Inflation]] -> 2.81 | AT22: =MacroData[[#This Row],[Core_Inflation]] -> 2.4 | AU22: =MacroData[[#This Row],[Food_Inflation]] -> 4.4 | AV22: =MacroData[[#This Row],[Non_Food_Inflation]] -> 1.8 | AW22: =MacroData[[#This Row],[PPI]] -> 1.1 | BB22: =MacroData[[#This Row],[Year]] -> 2019 | BC22: =MacroData[[#This Row],[Unemployment_Rate]] -> 6.31 | BD22: =MacroData[[#This Row],[Labour_Force_Part_Rate]] -> 36.3 | BE22: =MacroData[[#This Row],[Female_LFPR]] -> 49.85 | BF22: =INDEX(MacroData[Male_Wage_Growth], MATCH(Control!A24, MacroData[Year],0)) -> #N/A | BG22: =INDEX(MacroData[Female_Wage_Growth], MATCH(Control!A24, MacroData[Year],0)) -> #N/A | BH22: =INDEX(MacroData[Male_Wage_Growth], MATCH(Control!A24, MacroData[Year],0)) - INDEX(MacroData[Female_Wage_Growth], MATCH(Control!A24, MacroData[Year],0)) -> #N/A | BJ22: =MacroData[[#This Row],[Year]] -> 2019 | BK22: =MacroData[[#This Row],[Exports]] -> 62.54 | BL22: =MacroData[[#This Row],[Imports]] -> 125.29 | BM22: =MacroData[[#This Row],[Exchange_Rate_Movement]] -> 0.89 | BN22: =MacroData[[#This Row],[FDI]] -> 3.37 | BO22: =Table5[[#This Row],[Exports]] - Table5[[#This Row],[Imports]] -> -62.75 | BS22: =MacroData[[#This Row],[Year]] -> 2019 | BT22: =MacroData[[#This Row],[Gov_Expenditure]] -> 39 | BU22: =MacroData[[#This Row],[Budget_Deficit]] -> -0.4 | BV22: =MacroData[[#This Row],[Public_Debt]] -> 37.9 | BW22: =MacroData[[#This Row],[Revenue_Taxation]] -> 29
A23: 2020 | B23: =RIGHT(A23, 2) -> 20 | C23: =$C$28 -> 0.5236 | D23: =GETPIVOTDATA(""&D$1,Control!$W$3,"Year",""&$A23) -> -3.47 | E23: =GETPIVOTDATA(""&E$1,Control!$W$3,"Year",""&$A23) -> -2.08 | F23: =C23 -> 0.5236 | G23: =IFERROR(GETPIVOTDATA(""&D$1,Control!$B$3,"Year",""&$A23),NA()) -> #N/A | H23: =IFERROR(GETPIVOTDATA(""&E$1,Control!$B$3,"Year",""&$A23),NA()) -> #N/A | I23: =C23+G23 -> #N/A | J23: =IF(G23>1,TEXT(ROUND(G23/1,0),"0"),G23) -> #N/A | L23: =GETPIVOTDATA(""&L$1,Control!$B$36,"Year",""&$A23) -> 89.08 | M23: =GETPIVOTDATA(""&M$1,Control!$B$36,"Year",""&$A23) -> 83.9 | N23: =L23/SUM(L23:M23) -> 0.51497283 | T23: =GETPIVOTDATA(""&T$1,Control!$B$66,"Year",""&$A23) -> 62.66 | U23: =GETPIVOTDATA(""&U$1,Control!$C$66,"Year",""&$A23) -> 123.88 | V23: =T23/SUM(T23:U23) -> 0.33590651 | AB23: 4.01 | AC23: 22.05 | AD23: 73.04 | AJ23: =MacroData[[#This Row],[Year]] -> 2020 | AK23: =MacroData[[#This Row],[Policy_Interest_Rate]] -> 3.1 | AL23: =MacroData[[#This Row],[Market_Interest_Rate]] -> 3.1 | AN23: 2021 | AO23: 7.09 | AR23: =MacroData[[#This Row],[Year]] -> 2020 | AS23: =MacroData[[#This Row],[Headline_Inflation]] -> 0.22 | AT23: =MacroData[[#This Row],[Core_Inflation]] -> 0.8 | AU23: =MacroData[[#This Row],[Food_Inflation]] -> 1.8 | AV23: =MacroData[[#This Row],[Non_Food_Inflation]] -> -1.3 | AW23: =MacroData[[#This Row],[PPI]] -> -1.5 | BB23: =MacroData[[#This Row],[Year]] -> 2020 | BC23: =MacroData[[#This Row],[Unemployment_Rate]] -> 8.1 | BD23: =MacroData[[#This Row],[Labour_Force_Part_Rate]] -> 34.84 | BE23: =MacroData[[#This Row],[Female_LFPR]] -> 49.73 | BF23: =INDEX(MacroData[Male_Wage_Growth], MATCH(Control!A25, MacroData[Year],0)) -> #N/A | BG23: =INDEX(MacroData[Female_Wage_Growth], MATCH(Control!A25, MacroData[Year],0)) -> #N/A | BH23: =INDEX(MacroData[Male_Wage_Growth], MATCH(Control!A25, MacroData[Year],0)) - INDEX(MacroData[Female_Wage_Growth], MATCH(Control!A25, MacroData[Year],0)) -> #N/A | BJ23: =MacroData[[#This Row],[Year]] -> 2020 | BK23: =MacroData[[#This Row],[Exports]] -> 62.66 | BL23: =MacroData[[#This Row],[Imports]] -> 123.88 | BM23: =MacroData[[#This Row],[Exchange_Rate_Movement]] -> 0.87 | BN23: =MacroData[[#This Row],[FDI]] -> 2.81 | BO23: =Table5[[#This Row],[Exports]] - Table5[[#This Row],[Imports]] -> -61.22 | BS23: =MacroData[[#This Row],[Year]] -> 2020 | BT23: =MacroData[[#This Row],[Gov_Expenditure]] -> 42.6 | BU23: =MacroData[[#This Row],[Budget_Deficit]] -> -3.9 | BV23: =MacroData[[#This Row],[Public_Debt]] -> 44 | BW23: =MacroData[[#This Row],[Revenue_Taxation]] -> 30
A24: 2021 | B24: =RIGHT(A24, 2) -> 21 | C24: =$C$28 -> 0.5236 | D24: =GETPIVOTDATA(""&D$1,Control!$W$3,"Year",""&$A24) -> 6.94 | E24: =GETPIVOTDATA(""&E$1,Control!$W$3,"Year",""&$A24) -> 7.08 | F24: =C24 -> 0.5236 | G24: =IFERROR(GETPIVOTDATA(""&D$1,Control!$B$3,"Year",""&$A24),NA()) -> #N/A | H24: =IFERROR(GETPIVOTDATA(""&E$1,Control!$B$3,"Year",""&$A24),NA()) -> #N/A | I24: =C24+G24 -> #N/A | J24: =IF(G24>1,TEXT(ROUND(G24/1,0),"0"),G24) -> #N/A | L24: =GETPIVOTDATA(""&L$1,Control!$B$36,"Year",""&$A24) -> 89.28 | M24: =GETPIVOTDATA(""&M$1,Control!$B$36,"Year",""&$A24) -> 84.5 | N24: =L24/SUM(L24:M24) -> 0.51375302 | T24: =GETPIVOTDATA(""&T$1,Control!$B$66,"Year",""&$A24) -> 66.81 | U24: =GETPIVOTDATA(""&U$1,Control!$C$66,"Year",""&$A24) -> 136.8 | V24: =T24/SUM(T24:U24) -> 0.3281273 | AB24: 4.02 | AC24: 23.05 | AD24: 72.03 | AJ24: =MacroData[[#This Row],[Year]] -> 2021 | AK24: =MacroData[[#This Row],[Policy_Interest_Rate]] -> 2.8 | AL24: =MacroData[[#This Row],[Market_Interest_Rate]] -> 2.8 | AN24: 2022 | AO24: 6.04 | AR24: =MacroData[[#This Row],[Year]] -> 2021 | AS24: =MacroData[[#This Row],[Headline_Inflation]] -> 3.28 | AT24: =MacroData[[#This Row],[Core_Inflation]] -> 2 | AU24: =MacroData[[#This Row],[Food_Inflation]] -> 2.5 | AV24: =MacroData[[#This Row],[Non_Food_Inflation]] -> 4.8 | AW24: =MacroData[[#This Row],[PPI]] -> 13.5 | BB24: =MacroData[[#This Row],[Year]] -> 2021 | BC24: =MacroData[[#This Row],[Unemployment_Rate]] -> 7.51 | BD24: =MacroData[[#This Row],[Labour_Force_Part_Rate]] -> 32.71 | BE24: =MacroData[[#This Row],[Female_LFPR]] -> 49.39 | BF24: =INDEX(MacroData[Male_Wage_Growth], MATCH(Control!A26, MacroData[Year],0)) -> #N/A | BG24: =INDEX(MacroData[Female_Wage_Growth], MATCH(Control!A26, MacroData[Year],0)) -> #N/A | BH24: =INDEX(MacroData[Male_Wage_Growth], MATCH(Control!A26, MacroData[Year],0)) - INDEX(MacroData[Female_Wage_Growth], MATCH(Control!A26, MacroData[Year],0)) -> #N/A | BJ24: =MacroData[[#This Row],[Year]] -> 2021 | BK24: =MacroData[[#This Row],[Exports]] -> 66.81 | BL24: =MacroData[[#This Row],[Imports]] -> 136.8 | BM24: =MacroData[[#This Row],[Exchange_Rate_Movement]] -> 0.84 | BN24: =MacroData[[#This Row],[FDI]] -> 9.78 | BO24: =Table5[[#This Row],[Exports]] - Table5[[#This Row],[Imports]] -> -69.99 | BS24: =MacroData[[#This Row],[Year]] -> 2021 | BT24: =MacroData[[#This Row],[Gov_Expenditure]] -> 44.6 | BU24: =MacroData[[#This Row],[Budget_Deficit]] -> -5.7 | BV24: =MacroData[[#This Row],[Public_Debt]] -> 45.9 | BW24: =MacroData[[#This Row],[Revenue_Taxation]] -> 31
A25: 2022 | B25: =RIGHT(A25, 2) -> 22 | C25: =$C$28 -> 0.5236 | D25: =GETPIVOTDATA(""&D$1,Control!$W$3,"Year",""&$A25) -> 1.81 | E25: =GETPIVOTDATA(""&E$1,Control!$W$3,"Year",""&$A25) -> 2.01 | F25: =C25 -> 0.5236 | G25: =IFERROR(GETPIVOTDATA(""&D$1,Control!$B$3,"Year",""&$A25),NA()) -> #N/A | H25: =IFERROR(GETPIVOTDATA(""&E$1,Control!$B$3,"Year",""&$A25),NA()) -> #N/A | I25: =C25+G25 -> #N/A | J25: =IF(G25>1,TEXT(ROUND(G25/1,0),"0"),G25) -> #N/A | L25: =GETPIVOTDATA(""&L$1,Control!$B$36,"Year",""&$A25) -> 89.18 | M25: =GETPIVOTDATA(""&M$1,Control!$B$36,"Year",""&$A25) -> 84.82 | N25: =L25/SUM(L25:M25) -> 0.51252874 | T25: =GETPIVOTDATA(""&T$1,Control!$B$66,"Year",""&$A25) -> 77.48 | U25: =GETPIVOTDATA(""&U$1,Control!$C$66,"Year",""&$A25) -> 159.84 | V25: =T25/SUM(T25:U25) -> 0.32647902 | AB25: 4.03 | AC25: 22.08 | AD25: 72.09 | AJ25: =MacroData[[#This Row],[Year]] -> 2022 | AK25: =MacroData[[#This Row],[Policy_Interest_Rate]] -> 4.2 | AL25: =MacroData[[#This Row],[Market_Interest_Rate]] -> 4.2 | AN25: 2023 | AO25: 2.03 | AR25: =MacroData[[#This Row],[Year]] -> 2022 | AS25: =MacroData[[#This Row],[Headline_Inflation]] -> 17.31 | AT25: =MacroData[[#This Row],[Core_Inflation]] -> 9.5 | AU25: =MacroData[[#This Row],[Food_Inflation]] -> 21 | AV25: =MacroData[[#This Row],[Non_Food_Inflation]] -> 25.4 | AW25: =MacroData[[#This Row],[PPI]] -> 34 | BB25: =MacroData[[#This Row],[Year]] -> 2022 | BC25: =MacroData[[#This Row],[Unemployment_Rate]] -> 6.82 | BD25: =MacroData[[#This Row],[Labour_Force_Part_Rate]] -> 36.14 | BE25: =MacroData[[#This Row],[Female_LFPR]] -> 49.67 | BF25: =INDEX(MacroData[Male_Wage_Growth], MATCH(Control!A27, MacroData[Year],0)) -> #N/A | BG25: =INDEX(MacroData[Female_Wage_Growth], MATCH(Control!A27, MacroData[Year],0)) -> #N/A | BH25: =INDEX(MacroData[Male_Wage_Growth], MATCH(Control!A27, MacroData[Year],0)) - INDEX(MacroData[Female_Wage_Growth], MATCH(Control!A27, MacroData[Year],0)) -> #N/A | BJ25: =MacroData[[#This Row],[Year]] -> 2022 | BK25: =MacroData[[#This Row],[Exports]] -> 77.48 | BL25: =MacroData[[#This Row],[Imports]] -> 159.84 | BM25: =MacroData[[#This Row],[Exchange_Rate_Movement]] -> 0.95 | BN25: =MacroData[[#This Row],[FDI]] -> 3.2 | BO25: =Table5[[#This Row],[Exports]] - Table5[[#This Row],[Imports]] -> -82.36 | BS25: =MacroData[[#This Row],[Year]] -> 2022 | BT25: =MacroData[[#This Row],[Gov_Expenditure]] -> 43.5 | BU25: =MacroData[[#This Row],[Budget_Deficit]] -> -3.9 | BV25: =MacroData[[#This Row],[Public_Debt]] -> 44.4 | BW25: =MacroData[[#This Row],[Revenue_Taxation]] -> 32
A26: 2023 | B26: =RIGHT(A26, 2) -> 23 | C26: =$C$28 -> 0.5236 | D26: =GETPIVOTDATA(""&D$1,Control!$W$3,"Year",""&$A26) -> 2.85 | E26: =GETPIVOTDATA(""&E$1,Control!$W$3,"Year",""&$A26) -> 3 | F26: =C26 -> 0.5236 | G26: =IFERROR(GETPIVOTDATA(""&D$1,Control!$B$3,"Year",""&$A26),NA()) -> #N/A | H26: =IFERROR(GETPIVOTDATA(""&E$1,Control!$B$3,"Year",""&$A26),NA()) -> #N/A | I26: =C26+G26 -> #N/A | J26: =IF(G26>1,TEXT(ROUND(G26/1,0),"0"),G26) -> #N/A | L26: =GETPIVOTDATA(""&L$1,Control!$B$36,"Year",""&$A26) -> 89.16 | M26: =GETPIVOTDATA(""&M$1,Control!$B$36,"Year",""&$A26) -> 84.44 | N26: =L26/SUM(L26:M26) -> 0.51359447 | T26: =GETPIVOTDATA(""&T$1,Control!$B$66,"Year",""&$A26) -> 66.46 | U26: =GETPIVOTDATA(""&U$1,Control!$C$66,"Year",""&$A26) -> 136.63 | V26: =T26/SUM(T26:U26) -> 0.32724408 | AB26: 3.09 | AC26: 21.05 | AD26: 74.06 | AJ26: =MacroData[[#This Row],[Year]] -> 2023 | AK26: =MacroData[[#This Row],[Policy_Interest_Rate]] -> 5.8 | AL26: =MacroData[[#This Row],[Market_Interest_Rate]] -> 5.8 | AN26: 2024 | AO26: 6.06 | AR26: =MacroData[[#This Row],[Year]] -> 2023 | AS26: =MacroData[[#This Row],[Headline_Inflation]] -> 8.94 | AT26: =MacroData[[#This Row],[Core_Inflation]] -> 10 | AU26: =MacroData[[#This Row],[Food_Inflation]] -> 11 | AV26: =MacroData[[#This Row],[Non_Food_Inflation]] -> 10.2 | AW26: =MacroData[[#This Row],[PPI]] -> -4 | BB26: =MacroData[[#This Row],[Year]] -> 2023 | BC26: =MacroData[[#This Row],[Unemployment_Rate]] -> 6.47 | BD26: =MacroData[[#This Row],[Labour_Force_Part_Rate]] -> 34.94 | BE26: =MacroData[[#This Row],[Female_LFPR]] -> 49.7 | BF26: =INDEX(MacroData[Male_Wage_Growth], MATCH(Control!A28, MacroData[Year],0)) -> #N/A | BG26: =INDEX(MacroData[Female_Wage_Growth], MATCH(Control!A28, MacroData[Year],0)) -> #N/A | BH26: =INDEX(MacroData[Male_Wage_Growth], MATCH(Control!A28, MacroData[Year],0)) - INDEX(MacroData[Female_Wage_Growth], MATCH(Control!A28, MacroData[Year],0)) -> #N/A | BJ26: =MacroData[[#This Row],[Year]] -> 2023 | BK26: =MacroData[[#This Row],[Exports]] -> 66.46 | BL26: =MacroData[[#This Row],[Imports]] -> 136.63 | BM26: =MacroData[[#This Row],[Exchange_Rate_Movement]] -> 0.92 | BN26: =MacroData[[#This Row],[FDI]] -> 3.97 | BO26: =Table5[[#This Row],[Exports]] - Table5[[#This Row],[Imports]] -> -70.17 | BS26: =MacroData[[#This Row],[Year]] -> 2023 | BT26: =MacroData[[#This Row],[Gov_Expenditure]] -> 43.1 | BU26: =MacroData[[#This Row],[Budget_Deficit]] -> -3.4 | BV26: =MacroData[[#This Row],[Public_Debt]] -> 44.6 | BW26: =MacroData[[#This Row],[Revenue_Taxation]] -> 33
A27: 2024 | B27: =RIGHT(A27, 2) -> 24 | C27: =$C$28 -> 0.5236 | D27: =GETPIVOTDATA(""&D$1,Control!$W$3,"Year",""&$A27) -> -0.44 | E27: =GETPIVOTDATA(""&E$1,Control!$W$3,"Year",""&$A27) -> 0.04 | F27: =C27 -> 0.5236 | G27: =IFERROR(GETPIVOTDATA(""&D$1,Control!$B$3,"Year",""&$A27),NA()) -> #N/A | H27: =IFERROR(GETPIVOTDATA(""&E$1,Control!$B$3,"Year",""&$A27),NA()) -> #N/A | I27: =C27+G27 -> #N/A | J27: =IF(G27>1,TEXT(ROUND(G27/1,0),"0"),G27) -> #N/A | L27: =GETPIVOTDATA(""&L$1,Control!$B$36,"Year",""&$A27) -> 88.47 | M27: =GETPIVOTDATA(""&M$1,Control!$B$36,"Year",""&$A27) -> 84 | N27: =L27/SUM(L27:M27) -> 0.51295878 | T27: =GETPIVOTDATA(""&T$1,Control!$B$66,"Year",""&$A27) -> 64.62 | U27: =GETPIVOTDATA(""&U$1,Control!$C$66,"Year",""&$A27) -> 67.18 | V27: =T27/SUM(T27:U27) -> 0.49028832 | AB27: 4.01 | AC27: 21.02 | AD27: 74.07 | AJ27: =MacroData[[#This Row],[Year]] -> 2024 | AK27: =MacroData[[#This Row],[Policy_Interest_Rate]] -> 4.8 | AL27: =MacroData[[#This Row],[Market_Interest_Rate]] -> 4.8 | AR27: =MacroData[[#This Row],[Year]] -> 2024 | AS27: =MacroData[[#This Row],[Headline_Inflation]] -> 1.24 | AT27: =MacroData[[#This Row],[Core_Inflation]] -> 3.6 | AU27: =MacroData[[#This Row],[Food_Inflation]] -> 2.8 | AV27: =MacroData[[#This Row],[Non_Food_Inflation]] -> 0.5 | AW27: =MacroData[[#This Row],[PPI]] -> -3.8 | BB27: =MacroData[[#This Row],[Year]] -> 2024 | BC27: =MacroData[[#This Row],[Unemployment_Rate]] -> 6.72 | BD27: =MacroData[[#This Row],[Labour_Force_Part_Rate]] -> 34.7 | BE27: =MacroData[[#This Row],[Female_LFPR]] -> 49.84 | BF27: =INDEX(MacroData[Male_Wage_Growth], MATCH(Control!A29, MacroData[Year],0)) -> #N/A | BG27: =INDEX(MacroData[Female_Wage_Growth], MATCH(Control!A29, MacroData[Year],0)) -> #N/A | BH27: =INDEX(MacroData[Male_Wage_Growth], MATCH(Control!A29, MacroData[Year],0)) - INDEX(MacroData[Female_Wage_Growth], MATCH(Control!A29, MacroData[Year],0)) -> #N/A | BJ27: =MacroData[[#This Row],[Year]] -> 2024 | BK27: =MacroData[[#This Row],[Exports]] -> 64.62 | BL27: =MacroData[[#This Row],[Imports]] -> 67.18 | BM27: =MacroData[[#This Row],[Exchange_Rate_Movement]] -> 0.93 | BN27: =MacroData[[#This Row],[FDI]] -> 2.96 | BO27: =Table5[[#This Row],[Exports]] - Table5[[#This Row],[Imports]] -> -2.56 | BS27: =MacroData[[#This Row],[Year]] -> 2024 | BT27: =MacroData[[#This Row],[Gov_Expenditure]] -> 44.5 | BU27: =MacroData[[#This Row],[Budget_Deficit]] -> -1.8 | BV27: =MacroData[[#This Row],[Public_Debt]] -> 46.6 | BW27: =MacroData[[#This Row],[Revenue_Taxation]] -> 34.9
C28: =MAX(D2:E27)*4% -> 0.5236 | D28: =GETPIVOTDATA("Sum of Real_GDP_Growth",Control!$A$3) -> 26.22 | E28: =GETPIVOTDATA("Sum of GDP_Per_Capita_Growth",Control!$A$3) -> 37.22 | L28: =GETPIVOTDATA("Sum of Male_Wage_Growth",Control!$A$3) -> 890.11 | M28: =GETPIVOTDATA("Sum of Female_Wage_Growth",Control!$A$3) -> 836.56 | N28: =L28/SUM(L28:M28) -> 0.51550673 | T28: =GETPIVOTDATA("Sum of Exports",Control!$A$3) -> 517.93 | U28: =GETPIVOTDATA("Sum of Imports",Control!$A$3) -> 1129.22 | V28: =T28/SUM(T28:U28) -> 0.31444009 | AB28: =GETPIVOTDATA("Sum of Agriculture",Control!$A$3) -> 35.33 | AC28: =GETPIVOTDATA("Sum of Industry",Control!$A$3) -> 217.49 | AD28: =GETPIVOTDATA("Sum of Services",Control!$A$3) -> 736.38

Sheet Data
A1: Year | B1: Real_GDP_Growth | C1: GDP_Per_Capita_Growth | D1: Agriculture | E1: Industry | F1: Services | G1: Consumption_Contribution | H1: Policy_Interest_Rate | I1: Market_Interest_Rate | J1: Money_Supply | K1: Credit_Growth | L1: Headline_Inflation | M1: Core_Inflation | N1: Food_Inflation | O1: Non_Food_Inflation | P1: PPI | Q1: Unemployment_Rate | R1: Labour_Force_Part_Rate | S1: Female_LFPR | T1: Male_Wage_Growth | U1: Female_Wage_Growth | V1: Exports | W1: Imports | X1: Exchange_Rate_Movement | Y1: FDI | Z1: Gov_Expenditure | AA1: Budget_Deficit | AB1: Public_Debt | AC1: Revenue_Taxation
A2: 1999 | B2: 2.82 | C2: 3.07 | D2: 4.5 | E2: 23.08 | F2: 71.07 | G2: 63.08 | H2: 14.2 | I2: 14.2 | J2: 15 | K2: 15.3 | L2: 2.36 | M2: 2.9 | N2: -2 | O2: 4.1 | P2: -2 | Q2: 13.79 | R2: 42.32 | S2: 47.59 | T2: 83.11 | U2: 79.7 | V2: 36.03 | W2: 82.15 | X2: 0.58 | Y2: 4.75 | Z2: 40.4 | AA2: -3.5 | AB2: 14.8 | AC2: 21
A3: 2000 | B3: 5.84 | C3: 6.09 | D3: 4.09 | E3: 23.05 | F3: 71.06 | G3: 62.6 | H3: 12.5 | I3: 12.5 | J3: 28 | K3: 36.5 | L3: 2.65 | M3: 2.4 | N3: -0.1 | O3: 3.1 | P3: 0.6 | Q3: 14.21 | R3: 38.44 | S3: 48.04 | T3: 84.61 | U3: 81.48 | V3: 37.72 | W3: 83.61 | X3: 0.61 | Y3: 4.18 | Z3: 37 | AA3: -2.6 | AB3: 15.1 | AC3: 23
A4: 2001 | B4: 6.46 | C4: 7.08 | D4: 4.07 | E4: 23.01 | F4: 72.02 | G4: 63.3 | H4: 11.1 | I4: 11.1 | J4: 21 | K4: 48.2 | L4: 2.49 | M4: 2.2 | N4: 3.8 | O4: 2 | P4: 0.2 | Q4: 13.82 | R4: 37.4 | S4: 48.77 | T4: 84.25 | U4: 80.16 | V4: 38.8 | W4: 88.18 | X4: 0.62 | Y4: 2.12 | Z4: 35 | AA4: -2 | AB4: 17.8 | AC4: 25
A5: 2002 | B5: 7.67 | C5: 8.09 | D5: 4.07 | E5: 22.08 | F5: 72.05 | G5: 63.9 | H5: 8.8 | I5: 8.8 | J5: 21 | K5: 41.1 | L5: 1.94 | M5: 2 | N5: 1.5 | O5: 1.8 | P5: 1 | Q5: 13.83 | R5: 37.85 | S5: 48.74 | T5: 85.46 | U5: 80.83 | V5: 37.76 | W5: 85.98 | X5: 0.61 | Y5: 1.73 | Z5: 35.4 | AA5: -2.6 | AB5: 15.4 | AC5: 24
A6: 2003 | B6: 8.43 | C6: 9.05 | D6: 4.03 | E6: 22.01 | F6: 73.06 | G6: 64.9 | H6: 7.4 | I6: 7.4 | J6: 19 | K6: 52.5 | L6: 2.94 | M6: 2.1 | N6: 2.4 | O6: 3 | P6: 3.2 | Q6: 12.06 | R6: 38.87 | S6: 48.94 | T6: 85.6 | U6: 81.33 | V6: 37.74 | W6: 88.58 | X6: 0.57 | Y6: 2.82 | Z6: 34.4 | AA6: -1.7 | AB6: 15.4 | AC6: 23
A7: 2004 | B7: 8.73 | C7: 9.09 | D7: 4.05 | E7: 21.05 | F7: 74 | G7: 64.7 | H7: 6.9 | I7: 6.9 | J7: 27 | K7: 46 | L7: 6.19 | M7: 4.4 | N7: 9 | O7: 4.9 | P7: 6.5 | Q7: 11.71 | R7: 36.97 | S7: 48.54 | T7: 85.13 | U7: 82.02 | V7: 40.63 | W7: 97.24 | X7: 0.54 | Y7: 4.28 | Z7: 34.8 | AA7: -1 | AB7: 15.3 | AC7: 23
A8: 2005 | B8: 11.62 | C8: 12.08 | D8: 4.02 | E8: 21.03 | F8: 74.05 | G8: 65.3 | H8: 5.5 | I8: 5.5 | J8: 38 | K8: 62.7 | L8: 6.75 | M8: 5.1 | N8: 8.8 | O8: 5.9 | P8: 8.5 | Q8: 10.03 | R8: 38.05 | S8: 48.49 | T8: 87.79 | U8: 82.97 | V8: 44.81 | W8: 104.52 | X8: 0.56 | Y8: 4.97 | Z8: 35.8 | AA8: -1.1 | AB8: 12.5 | AC8: 24
A9: 2006 | B9: 12.83 | C9: 13.09 | D9: 3.06 | E9: 20.09 | F9: 75.05 | G9: 67.2 | H9: 6.2 | I9: 6.2 | J9: 41 | K9: 57 | L9: 6.54 | M9: 5.8 | N9: 9.5 | O9: 5.4 | P9: 10 | Q9: 7.03 | R9: 40.9 | S9: 48.47 | T9: 88.56 | U9: 83.74 | V9: 41.95 | W9: 105.7 | X9: 0.56 | Y9: 8.35 | Z9: 35.5 | AA9: -0.5 | AB9: 10.7 | AC9: 25
A10: 2007 | B10: 10.41 | C10: 11.03 | D10: 3.03 | E10: 20.06 | F10: 76.01 | G10: 66.3 | H10: 8.5 | I10: 8.5 | J10: 13 | K10: 34.2 | L10: 10.09 | M10: 9 | N10: 12.3 | O10: 9.1 | P10: 15 | Q10: 6.05 | R10: 42.64 | S10: 48.29 | T10: 88.94 | U10: 84.17 | V10: 40.39 | W10: 100.88 | X10: 0.51 | Y10: 9.22 | Z10: 34.8 | AA10: 0.6 | AB10: 9 | AC10: 26
A11: 2008 | B11: -3.39 | C11: -2.04 | D11: 3.01 | E11: 20.08 | F11: 76.01 | G11: 64.1 | H11: 11.4 | I11: 11.4 | J11: -2 | K11: 12.3 | L11: 15.04 | M11: 13.5 | N11: 19.5 | O11: 13.1 | P11: 12 | Q11: 7.74 | R11: 42.87 | S11: 48.98 | T11: 89.88 | U11: 84.36 | V11: 41.23 | W11: 95.77 | X11: 0.48 | Y11: 4.2 | Z11: 38.2 | AA11: -3.3 | AB11: 19.3 | AC11: 26
A12: 2009 | B12: -16.04 | C12: -14.06 | D12: 3.04 | E12: 20.02 | F12: 76.04 | G12: 61.3 | H12: 14.8 | I12: 14.8 | J12: -5 | K12: -7.4 | L12: 3.53 | M12: 3.8 | N12: 2.1 | O12: 1.4 | P12: -3.5 | Q12: 17.52 | R12: 41.25 | S12: 49.8 | T12: 89.25 | U12: 83.54 | V12: 43.4 | W12: 88.83 | X12: 0.51 | Y12: -0.58 | Z12: 43.6 | AA12: -7.1 | AB12: 37.6 | AC12: 24
A13: 2010 | B13: -3.66 | C13: -1.06 | D13: 4.01 | E13: 22.06 | F13: 73.03 | G13: 61.6 | H13: 9.2 | I13: 9.2 | J13: 7 | K13: -8.8 | L13: -1.08 | M13: -2.5 | N13: 1 | O13: -2.2 | P13: 1.4 | Q13: 19.48 | R13: 39.75 | S13: 50.39 | T13: 88.88 | U13: 83.57 | V13: 54.37 | W13: 110.86 | X13: 0.53 | Y13: 2.02 | Z13: 43.6 | AA13: -6.6 | AB13: 48.2 | AC13: 23
... A27: 2024 | B27: -0.44 | C27: 0.04 | D27: 4.01 | E27: 21.02 | F27: 74.07 | G27: 62.1 | H27: 4.8 | I27: 4.8 | J27: 6.06 | K27: 5.5 | L27: 1.24 | M27: 3.6 | N27: 2.8 | O27: 0.5 | P27: -3.8 | Q27: 6.72 | R27: 34.7 | S27: 49.84 | T27: 88.47 | U27: 84 | V27: 64.62 | W27: 67.18 | X27: 0.93 | Y27: 2.96 | Z27: 44.5 | AA27: -1.8 | AB27: 46.6 | AC27: 34.9

Sheet Resources
B1: Colors | C1: Position | D1: Angle | E1: Transparency | G1: Shadow | H1: 0.2 | I1: 100 | J1: 35 | K1: 135 | L1: 15 | P1: $#,##0;-$#,##0;0 | R1: [>=1000]0,"k";[<=-1000]-0,"k";0
B2: #12143D | G2: Shadow | H2: 0.2 | I2: 100 | J2: 35 | K2: 135 | L2: 8
B3: #1F2357 | C3: 0 | D3: 135 | G3: Shadow | H3: 0.2 | I3: 100 | J3: 15 | K3: 135 | L3: 15
B4: #10123B | C4: 75 | D4: 135
A5: Line | B5: #4647A6 | C5: 0 | D5: 135 | F5: https://exceltable.com/
A6: Line | B6: #333787 | C6: 100 | D6: 135
B8: #20245A | C8: 0 | D8: 135
B9: #10123B | C9: 75 | D9: 135
A10: Line | B10: #B9C1FF | C10: 0 | D10: 150
A11: Line | B11: #3D4098 | C11: 33 | D11: 150
A12: Line | B12: #333787 | C12: 100 | D12: 150
B14: #323687 | C14: 0 | D14: 110
B15: #10123A | C15: 75 | D15: 110
A16: Line | B16: #A2D8F0 | C16: 0 | D16: 135
A17: Line | B17: #5D63D1 | C17: 38 | D17: 135
A18: Line | B18: #2E327A | C18: 100 | D18: 135
B20: #CEC5FF
B21: #6372A4
B22: #0575F1
B24: #22255C | C24: 0 | D24: 0
B25: #2C3076 | C25: 5 | D25: 0
B26: #2C3076 | C26: 97 | D26: 0
B27: #323687 | C27: 100 | D27: 0
A28: Line | B28: #A2D8F0 | C28: 0 | D28: 135
A29: Line | B29: #5D63D1 | C29: 38 | D29: 135
A30: Line | B30: #2E327A | C30: 100 | D30: 135
B31: #2069F0
B32: #9933FF
B34: #22248D | C34: 10 | D34: 135
B35: #060839 | C35: 67 | D35: 135
A36: Line | B36: #7079FF | C36: 25 | D36: 135
A37: Line | B37: #1C1D86 | C37: 100 | D37: 135
B39: #374AEC
B40: #1B2399
B41: #7C93FD
B42: #4641D1
B43: #0093CE
B44: #FF00FF
B46: #808AEC | C46: 10 | D46: 90
B47: #4A59E4 | C47: 80 | D47: 90
B48: #FF00FF | C48: 0 | D48: 90 | E48: 0
B49: #FF00FF | C49: 88 | D49: 90 | E49: 50
B51: #0070B1 | C51: 0 | D51: 90
B52: #00B7D2 | C52: 100 | D52: 90
B53: #3647E3 | C53: 0 | D53: 90
B54: #8D76FC | C54: 100 | D54: 90
B55: #3A5CE2 | C55: 0 | D55: 90
B56: #476BEE | C56: 100 | D56: 90
B57: #8701DA | C57: 0 | D57: 90
B58: #AD27FE | C58: 100 | D58: 90
B59: #34349E | C59: 0 | D59: 90
B60: #212469 | C60: 100 | D60: 90
B62: #476BEE
B63: #3A5CE2
B64: #8199F3
B65: #CAD4FA
